Workbook

Sheet Template_import_matherial
A1: ID | B1: Material | C1: Model | D1: Unit type | E1: SalesArea | F1: Sale office | G1: Catologue Yes/Not | H1: Nota Descritiva | I1: Note Aggiuntive | J1: Min Q.tà | K1: Area | L1: Avviament1 | M1: Accessori | N1: Famiglia | O1: Tipologia | P1: Tecnologia | Q1: catalogo | R1: dimensionali | S1: Scheda Tecnica
D2: INT/EXT | E2: HN|RN,CN | F2: ABI0,ABI1, ... | L2: EE22, TT76 | M2: Z34,X53,S12 | U2: Seperatore:|
A9: Riga che arriva da SAP attraverso MATMAS
A10: ID | B10: Material | C10: Model | D10: Unit type | E10: SalesArea | F10: Sale office | G10: Catologue Yes/Not | H10: Nota Descritiva | I10: Note Aggiuntive | J10: Min Q.tà | K10: Area | L10: Avviament1 | M10: Accessori | N10: Famiglia | O10: Tipologia | P10: Tecnologia | Q10: catalogo | R10: dimensionali | S10: Scheda Tecnica
A11: last+1 | G11: No
O12: Deve essere possibile vedere le righe entrate da MATMAS e non trattate
O13: Considero righe con Sales area o Sales office vuoto
O14: Per queste righe, all'import dfei file di disponibilità non vengono generate righe aggiuntive
O15: la priorità per le righe inserite da matmas è l'ultima + 1

Sheet Matrice Visualizzazione File 1
B1: Filtro esposto | C1: Filtro esposto | D1: Filtro esposto | E1: Filtro esposto | H1: Esposti limitati in base al profilo utente | Q1: Esposti limitati in base al profilo utente | R1: Filtro | U1: Filtro
H2: Filtro -agente: vede solo prodotti disponibili nei sales office da ZZ_SALES_RES -operatori: tutto - area manager: solo sales office legati ai propri agenti in sales area HN + HD + CN | R2: Aggiungerte alla riga dati
A3: matherial | B3: matherial | C3: matherial | D3: matherial
A4: Ordine | B4: ID | C4: Descizione | D4: int/ext | H4: Linea 1 | I4: MRV | J4: A2W | K4: HEC | L4: ENERGY | M4: Retail | N4: ROE | O4: Service | P4: Water Heater | Q4: Se yes => è pubblico | V4: Digitare Codice | W4: Non Toccare | X4: Digitare Codice | Y4: Non Toccare | Z4: Digitare Codice | AA4: Non Toccare | AB4: Digitare Codice | AC4: Non Toccare | AD4: Digitare Codice | AE4: Non Toccare | AF4: Digitare Codice | AG4: Non Toccare | AH4: Digitare Codice | AI4: Non Toccare | AJ4: Dati Filtri / Capitolato
A5: ID | B5: Material | C5: Model | D5: Unit type | E5: HN | F5: RN | G5: CN | H5: Sale office 1 | I5: Sale Office 2 | J5: Sale office 3 | K5: Sale office 4 | L5: Sale office 5 | M5: Sale office 6 | N5: Sale office 7 | O5: Sale office 8 | P5: Sale office 9 | Q5: InCatalog | R5: Nota Descritiva | S5: Note Aggiuntive | T5: Min Q.tà | U5: Area | V5: Codice Avviamento 1 | W5: Codice Avviamento Descrizione 1 | X5: Codice Avviamento 2 | Y5: Codice Avviamento Descrizione 2 | Z5: Accessorio 1 | AA5: Accessorio Descrizione 1 | AB5: Accessorio 2 | AC5: Accessorio Descrizione 2 | AD5: Accessorio 3 | AE5: Accessorio Descrizione 3 | AF5: Accessorio 4 | AG5: Accessorio Descrizione 4 | AH5: Accessorio 5 | AI5: Accessorio Descrizione 5 | AJ5: Famiglia | AK5: Tipologia | AL5: Tecnologia | AM5: Catalogo | AN5: Dimensionali | AO5: Scheda Tecnica | AP5: Descrizione Capitolato | AQ5: Descrizione Capitolato Opzionale
A6: 1 | B6: AB97Y0E00 | C6: AP71DFMHRA DIZUN | D6: IU | E6: HN | F6: RN | H6: ABI0 | N6: AGIR | O6: ASI0 | Q6: Yes | R6: Cabinet | T6: 5 | U6: Catologue | W6: =IFERROR(VLOOKUP(V:V,$B:$C,2,),"") | Y6: =IFERROR(VLOOKUP(X:X,$B:$C,2,),"") | AA6: =IFERROR(VLOOKUP(Z:Z,$B:$C,2,),"") | AC6: =IFERROR(VLOOKUP(AB:AB,$B:$C,2,),"") | AE6: =IFERROR(VLOOKUP(AD:AD,$B:$C,2,),"") | AG6: =IFERROR(VLOOKUP(AF:AF,$B:$C,2,),"") | AI6: =IFERROR(VLOOKUP(AH:AH,$B:$C,2,),"")
A7: =A6+1 -> 2 | B7: AACKF0E00 | C7: 1U71WEMFRA DIZUN | D7: OU | E7: HN | F7: RN | H7: ABI0 | N7: AGIR | O7: ASI0 | Q7: Yes | R7: Cabinet | T7: 5 | U7: Catologue | W7: =IFERROR(VLOOKUP(V:V,$B:$C,2,),"") | Y7: =IFERROR(VLOOKUP(X:X,$B:$C,2,),"") | AA7: =IFERROR(VLOOKUP(Z:Z,$B:$C,2,),"") | AC7: =IFERROR(VLOOKUP(AB:AB,$B:$C,2,),"") | AE7: =IFERROR(VLOOKUP(AD:AD,$B:$C,2,),"") | AG7: =IFERROR(VLOOKUP(AF:AF,$B:$C,2,),"") | AI7: =IFERROR(VLOOKUP(AH:AH,$B:$C,2,),"")
A8: =A7+1 -> 3 | E8: --- | F8: --- | W8: =IFERROR(VLOOKUP(V:V,$B:$C,2,),"") | Y8: =IFERROR(VLOOKUP(X:X,$B:$C,2,),"") | AA8: =IFERROR(VLOOKUP(Z:Z,$B:$C,2,),"") | AC8: =IFERROR(VLOOKUP(AB:AB,$B:$C,2,),"") | AE8: =IFERROR(VLOOKUP(AD:AD,$B:$C,2,),"") | AG8: =IFERROR(VLOOKUP(AF:AF,$B:$C,2,),"") | AI8: =IFERROR(VLOOKUP(AH:AH,$B:$C,2,),"")
A9: =A8+1 -> 4 | B9: AAC160E00 | D9: IU | E9: HN | F9: RN | H9: ABI0 | N9: AGIR | O9: ASI0 | Q9: Yes | R9: Expert Nordic | T9: 5 | U9: Catologue | W9: =IFERROR(VLOOKUP(V:V,$B:$C,2,),"") | Y9: =IFERROR(VLOOKUP(X:X,$B:$C,2,),"") | AA9: =IFERROR(VLOOKUP(Z:Z,$B:$C,2,),"") | AC9: =IFERROR(VLOOKUP(AB:AB,$B:$C,2,),"") | AE9: =IFERROR(VLOOKUP(AD:AD,$B:$C,2,),"") | AG9: =IFERROR(VLOOKUP(AF:AF,$B:$C,2,),"") | AI9: =IFERROR(VLOOKUP(AH:AH,$B:$C,2,),"")
A10: =A9+1 -> 5 | B10: AAC180E00 | C10: 1U25KEHFRA-NR | D10: OU | E10: HN | F10: RN | H10: ABI0 | N10: AGIR | O10: ASI0 | Q10: Yes | R10: Expert Nordic | T10: 5 | U10: Catologue | W10: =IFERROR(VLOOKUP(V:V,$B:$C,2,),"") | Y10: =IFERROR(VLOOKUP(X:X,$B:$C,2,),"") | AA10: =IFERROR(VLOOKUP(Z:Z,$B:$C,2,),"") | AC10: =IFERROR(VLOOKUP(AB:AB,$B:$C,2,),"") | AE10: =IFERROR(VLOOKUP(AD:AD,$B:$C,2,),"") | AG10: =IFERROR(VLOOKUP(AF:AF,$B:$C,2,),"") | AI10: =IFERROR(VLOOKUP(AH:AH,$B:$C,2,),"")
A11: =A10+1 -> 6 | B11: AAC170E00 | C11: AS35XCHHRA-NR | D11: IU | E11: HN | F11: RN | H11: ABI0 | N11: AGIR | O11: ASI0 | Q11: Yes | R11: Expert Nordic | T11: 5 | U11: Catologue | W11: =IFERROR(VLOOKUP(V:V,$B:$C,2,),"") | Y11: =IFERROR(VLOOKUP(X:X,$B:$C,2,),"") | AA11: =IFERROR(VLOOKUP(Z:Z,$B:$C,2,),"") | AC11: =IFERROR(VLOOKUP(AB:AB,$B:$C,2,),"") | AE11: =IFERROR(VLOOKUP(AD:AD,$B:$C,2,),"") | AG11: =IFERROR(VLOOKUP(AF:AF,$B:$C,2,),"") | AI11: =IFERROR(VLOOKUP(AH:AH,$B:$C,2,),"")
A12: =A11+1 -> 7 | B12: AAC190E00 | C12: 1U35KEHFRA-NR | D12: OU | E12: HN | F12: RN | H12: ABI0 | N12: AGIR | O12: ASI0 | Q12: Yes | R12: Expert Nordic | T12: 5 | U12: Catologue | W12: =IFERROR(VLOOKUP(V:V,$B:$C,2,),"") | Y12: =IFERROR(VLOOKUP(X:X,$B:$C,2,),"") | AA12: =IFERROR(VLOOKUP(Z:Z,$B:$C,2,),"") | AC12: =IFERROR(VLOOKUP(AB:AB,$B:$C,2,),"") | AE12: =IFERROR(VLOOKUP(AD:AD,$B:$C,2,),"") | AG12: =IFERROR(VLOOKUP(AF:AF,$B:$C,2,),"") | AI12: =IFERROR(VLOOKUP(AH:AH,$B:$C,2,),"")
A13: =A12+1 -> 8 | B13: AABQN6E00 | C13: 1U35MEHFRA-1 | D13: OU | F13: RN | N13: AGIR | O13: ASI0 | Q13: Yes | R13: Flexis Nordic | T13: 5 | U13: Catologue | W13: =IFERROR(VLOOKUP(V:V,$B:$C,2,),"") | Y13: =IFERROR(VLOOKUP(X:X,$B:$C,2,),"") | AA13: =IFERROR(VLOOKUP(Z:Z,$B:$C,2,),"") | AC13: =IFERROR(VLOOKUP(AB:AB,$B:$C,2,),"") | AE13: =IFERROR(VLOOKUP(AD:AD,$B:$C,2,),"") | AG13: =IFERROR(VLOOKUP(AF:AF,$B:$C,2,),"") | AI13: =IFERROR(VLOOKUP(AH:AH,$B:$C,2,),"")
A14: =A13+1 -> 9 | B14: AAC152E00 | C14: 1U50KEFFRA-1 | D14: OU | F14: RN | N14: AGIR | O14: ASI0 | Q14: Yes | R14: Flexis Nordic | T14: 5 | U14: Catologue | W14: =IFERROR(VLOOKUP(V:V,$B:$C,2,),"") | Y14: =IFERROR(VLOOKUP(X:X,$B:$C,2,),"") | AA14: =IFERROR(VLOOKUP(Z:Z,$B:$C,2,),"") | AC14: =IFERROR(VLOOKUP(AB:AB,$B:$C,2,),"") | AE14: =IFERROR(VLOOKUP(AD:AD,$B:$C,2,),"") | AG14: =IFERROR(VLOOKUP(AF:AF,$B:$C,2,),"") | AI14: =IFERROR(VLOOKUP(AH:AH,$B:$C,2,),"")
A15: =A14+1 -> 10 | E15: --- | F15: --- | W15: =IFERROR(VLOOKUP(V:V,$B:$C,2,),"") | Y15: =IFERROR(VLOOKUP(X:X,$B:$C,2,),"") | AA15: =IFERROR(VLOOKUP(Z:Z,$B:$C,2,),"") | AC15: =IFERROR(VLOOKUP(AB:AB,$B:$C,2,),"") | AE15: =IFERROR(VLOOKUP(AD:AD,$B:$C,2,),"") | AG15: =IFERROR(VLOOKUP(AF:AF,$B:$C,2,),"") | AI15: =IFERROR(VLOOKUP(AH:AH,$B:$C,2,),"")
A16: =A15+1 -> 11 | B16: AACCP0E00 | C16: AS25PCHHRA-NR | D16: IU | F16: RN | N16: AGIR | O16: ASI0 | Q16: Yes | R16: Pearl Nordic | T16: 5 | U16: Catologue | W16: =IFERROR(VLOOKUP(V:V,$B:$C,2,),"") | Y16: =IFERROR(VLOOKUP(X:X,$B:$C,2,),"") | AA16: =IFERROR(VLOOKUP(Z:Z,$B:$C,2,),"") | AC16: =IFERROR(VLOOKUP(AB:AB,$B:$C,2,),"") | AE16: =IFERROR(VLOOKUP(AD:AD,$B:$C,2,),"") | AG16: =IFERROR(VLOOKUP(AF:AF,$B:$C,2,),"") | AI16: =IFERROR(VLOOKUP(AH:AH,$B:$C,2,),"")
A17: =A16+1 -> 12 | B17: AACCQ0E00 | C17: AS35PCHHRA-NR | D17: IU | F17: RN | N17: AGIR | O17: ASI0 | Q17: Yes | R17: Pearl Nordic | T17: 5 | U17: Catologue | W17: =IFERROR(VLOOKUP(V:V,$B:$C,2,),"") | Y17: =IFERROR(VLOOKUP(X:X,$B:$C,2,),"") | AA17: =IFERROR(VLOOKUP(Z:Z,$B:$C,2,),"") | AC17: =IFERROR(VLOOKUP(AB:AB,$B:$C,2,),"") | AE17: =IFERROR(VLOOKUP(AD:AD,$B:$C,2,),"") | AG17: =IFERROR(VLOOKUP(AF:AF,$B:$C,2,),"") | AI17: =IFERROR(VLOOKUP(AH:AH,$B:$C,2,),"")
A18: =A17+1 -> 13 | B18: AACCR0E00 | C18: AS50PDHHRA-NR | D18: IU | F18: RN | N18: AGIR | O18: ASI0 | Q18: Yes | R18: Pearl Nordic | T18: 5 | U18: Catologue | W18: =IFERROR(VLOOKUP(V:V,$B:$C,2,),"") | Y18: =IFERROR(VLOOKUP(X:X,$B:$C,2,),"") | AA18: =IFERROR(VLOOKUP(Z:Z,$B:$C,2,),"") | AC18: =IFERROR(VLOOKUP(AB:AB,$B:$C,2,),"") | AE18: =IFERROR(VLOOKUP(AD:AD,$B:$C,2,),"") | AG18: =IFERROR(VLOOKUP(AF:AF,$B:$C,2,),"") | AI18: =IFERROR(VLOOKUP(AH:AH,$B:$C,2,),"")
A19: =A18+1 -> 14 | B19: AACCS0E00 | C19: 1U25KEFFRA-NR | D19: OU | F19: RN | N19: AGIR | O19: ASI0 | Q19: Yes | R19: Pearl Nordic | T19: 5 | U19: Catologue | W19: =IFERROR(VLOOKUP(V:V,$B:$C,2,),"") | Y19: =IFERROR(VLOOKUP(X:X,$B:$C,2,),"") | AA19: =IFERROR(VLOOKUP(Z:Z,$B:$C,2,),"") | AC19: =IFERROR(VLOOKUP(AB:AB,$B:$C,2,),"") | AE19: =IFERROR(VLOOKUP(AD:AD,$B:$C,2,),"") | AG19: =IFERROR(VLOOKUP(AF:AF,$B:$C,2,),"") | AI19: =IFERROR(VLOOKUP(AH:AH,$B:$C,2,),"")
A20: =A19+1 -> 15 | B20: AACCT0E00 | C20: 1U35KEFFRA-NR | D20: OU | F20: RN | N20: AGIR | O20: ASI0 | Q20: Yes | R20: Pearl Nordic | T20: 5 | U20: Catologue | W20: =IFERROR(VLOOKUP(V:V,$B:$C,2,),"") | Y20: =IFERROR(VLOOKUP(X:X,$B:$C,2,),"") | AA20: =IFERROR(VLOOKUP(Z:Z,$B:$C,2,),"") | AC20: =IFERROR(VLOOKUP(AB:AB,$B:$C,2,),"") | AE20: =IFERROR(VLOOKUP(AD:AD,$B:$C,2,),"") | AG20: =IFERROR(VLOOKUP(AF:AF,$B:$C,2,),"") | AI20: =IFERROR(VLOOKUP(AH:AH,$B:$C,2,),"")
A21: =A20+1 -> 16 | B21: AACCU0E00 | C21: 1U50WEFFRA-NR | D21: OU | F21: RN | N21: AGIR | O21: ASI0 | Q21: Yes | R21: Pearl Nordic | T21: 5 | U21: Catologue | W21: =IFERROR(VLOOKUP(V:V,$B:$C,2,),"") | Y21: =IFERROR(VLOOKUP(X:X,$B:$C,2,),"") | AA21: =IFERROR(VLOOKUP(Z:Z,$B:$C,2,),"") | AC21: =IFERROR(VLOOKUP(AB:AB,$B:$C,2,),"") | AE21: =IFERROR(VLOOKUP(AD:AD,$B:$C,2,),"") | AG21: =IFERROR(VLOOKUP(AF:AF,$B:$C,2,),"") | AI21: =IFERROR(VLOOKUP(AH:AH,$B:$C,2,),"")
A22: =A21+1 -> 17 | E22: --- | F22: --- | W22: =IFERROR(VLOOKUP(V:V,$B:$C,2,),"") | Y22: =IFERROR(VLOOKUP(X:X,$B:$C,2,),"") | AA22: =IFERROR(VLOOKUP(Z:Z,$B:$C,2,),"") | AC22: =IFERROR(VLOOKUP(AB:AB,$B:$C,2,),"") | AE22: =IFERROR(VLOOKUP(AD:AD,$B:$C,2,),"") | AG22: =IFERROR(VLOOKUP(AF:AF,$B:$C,2,),"") | AI22: =IFERROR(VLOOKUP(AH:AH,$B:$C,2,),"")
A23: =A22+1 -> 18 | B23: AAC110E00 | C23: AS25PBBHRA | D23: IU | F23: RN | N23: AGIR | O23: ASI0 | Q23: Yes | R23: Pearl R290 | T23: 5 | U23: Catologue | W23: =IFERROR(VLOOKUP(V:V,$B:$C,2,),"") | Y23: =IFERROR(VLOOKUP(X:X,$B:$C,2,),"") | AA23: =IFERROR(VLOOKUP(Z:Z,$B:$C,2,),"") | AC23: =IFERROR(VLOOKUP(AB:AB,$B:$C,2,),"") | AE23: =IFERROR(VLOOKUP(AD:AD,$B:$C,2,),"") | AG23: =IFERROR(VLOOKUP(AF:AF,$B:$C,2,),"") | AI23: =IFERROR(VLOOKUP(AH:AH,$B:$C,2,),"")
A24: =A23+1 -> 19 | B24: AAC120E00 | C24: 1U25YEBGRA | D24: OU | F24: RN | N24: AGIR | O24: ASI0 | Q24: Yes | R24: Pearl R290 | T24: 5 | U24: Catologue | W24: =IFERROR(VLOOKUP(V:V,$B:$C,2,),"") | Y24: =IFERROR(VLOOKUP(X:X,$B:$C,2,),"") | AA24: =IFERROR(VLOOKUP(Z:Z,$B:$C,2,),"") | AC24: =IFERROR(VLOOKUP(AB:AB,$B:$C,2,),"") | AE24: =IFERROR(VLOOKUP(AD:AD,$B:$C,2,),"") | AG24: =IFERROR(VLOOKUP(AF:AF,$B:$C,2,),"") | AI24: =IFERROR(VLOOKUP(AH:AH,$B:$C,2,),"")
A25: =A24+1 -> 20 | B25: AAC130E00 | C25: AS35PBBHRA | D25: IU | F25: RN | N25: AGIR | O25: ASI0 | Q25: Yes | R25: Pearl R290 | T25: 5 | U25: Catologue | W25: =IFERROR(VLOOKUP(V:V,$B:$C,2,),"") | Y25: =IFERROR(VLOOKUP(X:X,$B:$C,2,),"") | AA25: =IFERROR(VLOOKUP(Z:Z,$B:$C,2,),"") | AC25: =IFERROR(VLOOKUP(AB:AB,$B:$C,2,),"") | AE25: =IFERROR(VLOOKUP(AD:AD,$B:$C,2,),"") | AG25: =IFERROR(VLOOKUP(AF:AF,$B:$C,2,),"") | AI25: =IFERROR(VLOOKUP(AH:AH,$B:$C,2,),"")
A26: =A25+1 -> 21 | B26: AAC140E00 | C26: 1U35YEBGRA | D26: OU | F26: RN | N26: AGIR | O26: ASI0 | Q26: Yes | R26: Pearl R290 | T26: 5 | U26: Catologue | W26: =IFERROR(VLOOKUP(V:V,$B:$C,2,),"") | Y26: =IFERROR(VLOOKUP(X:X,$B:$C,2,),"") | AA26: =IFERROR(VLOOKUP(Z:Z,$B:$C,2,),"") | AC26: =IFERROR(VLOOKUP(AB:AB,$B:$C,2,),"") | AE26: =IFERROR(VLOOKUP(AD:AD,$B:$C,2,),"") | AG26: =IFERROR(VLOOKUP(AF:AF,$B:$C,2,),"") | AI26: =IFERROR(VLOOKUP(AH:AH,$B:$C,2,),"")
A27: =A26+1 -> 22 | E27: --- | F27: --- | W27: =IFERROR(VLOOKUP(V:V,$B:$C,2,),"") | Y27: =IFERROR(VLOOKUP(X:X,$B:$C,2,),"") | AA27: =IFERROR(VLOOKUP(Z:Z,$B:$C,2,),"") | AC27: =IFERROR(VLOOKUP(AB:AB,$B:$C,2,),"") | AE27: =IFERROR(VLOOKUP(AD:AD,$B:$C,2,),"") | AG27: =IFERROR(VLOOKUP(AF:AF,$B:$C,2,),"") | AI27: =IFERROR(VLOOKUP(AH:AH,$B:$C,2,),"")
A28: =A27+1 -> 23 | B28: AABQM0E00 | C28: 1U25S2SM1FA-2 | D28: OU | E28: HN | F28: RN | H28: ABI0 | N28: AGIR | O28: ASI0 | Q28: Yes | R28: Mono SM+ | T28: 30 | U28: Catologue | W28: =IFERROR(VLOOKUP(V:V,$B:$C,2,),"") | Y28: =IFERROR(VLOOKUP(X:X,$B:$C,2,),"") | AA28: =IFERROR(VLOOKUP(Z:Z,$B:$C,2,),"") | AC28: =IFERROR(VLOOKUP(AB:AB,$B:$C,2,),"") | AE28: =IFERROR(VLOOKUP(AD:AD,$B:$C,2,),"") | AG28: =IFERROR(VLOOKUP(AF:AF,$B:$C,2,),"") | AI28: =IFERROR(VLOOKUP(AH:AH,$B:$C,2,),"")
A29: =A28+1 -> 24 | B29: AABQN0E00 | C29: 1U35S2SM1FA-2 | D29: OU | E29: HN | F29: RN | H29: ABI0 | N29: AGIR | O29: ASI0 | Q29: Yes | R29: Mono SM+ | T29: 30 | U29: Catologue | W29: =IFERROR(VLOOKUP(V:V,$B:$C,2,),"") | Y29: =IFERROR(VLOOKUP(X:X,$B:$C,2,),"") | AA29: =IFERROR(VLOOKUP(Z:Z,$B:$C,2,),"") | AC29: =IFERROR(VLOOKUP(AB:AB,$B:$C,2,),"") | AE29: =IFERROR(VLOOKUP(AD:AD,$B:$C,2,),"") | AG29: =IFERROR(VLOOKUP(AF:AF,$B:$C,2,),"") | AI29: =IFERROR(VLOOKUP(AH:AH,$B:$C,2,),"")
A30: =A29+1 -> 25 | B30: AAAYV0E09 | C30: 1U42S2SM1FA | D30: OU | E30: HN | F30: RN | H30: ABI0 | N30: AGIR | O30: ASI0 | Q30: Yes | R30: Mono SM+ | T30: 30 | U30: Catologue | W30: =IFERROR(VLOOKUP(V:V,$B:$C,2,),"") | Y30: =IFERROR(VLOOKUP(X:X,$B:$C,2,),"") | AA30: =IFERROR(VLOOKUP(Z:Z,$B:$C,2,),"") | AC30: =IFERROR(VLOOKUP(AB:AB,$B:$C,2,),"") | AE30: =IFERROR(VLOOKUP(AD:AD,$B:$C,2,),"") | AG30: =IFERROR(VLOOKUP(AF:AF,$B:$C,2,),"") | AI30: =IFERROR(VLOOKUP(AH:AH,$B:$C,2,),"")
A31: =A30+1 -> 26 | B31: AAC150E00 | C31: 1U50S2SJ2FA-2 | D31: OU | E31: HN | F31: RN | H31: ABI0 | M31: ACI0 | N31: AGIR | O31: ASI0 | Q31: Yes | R31: Mono SM+ | T31: 30 | U31: Catologue | W31: =IFERROR(VLOOKUP(V:V,$B:$C,2,),"") | Y31: =IFERROR(VLOOKUP(X:X,$B:$C,2,),"") | AA31: =IFERROR(VLOOKUP(Z:Z,$B:$C,2,),"") | AC31: =IFERROR(VLOOKUP(AB:AB,$B:$C,2,),"") | AE31: =IFERROR(VLOOKUP(AD:AD,$B:$C,2,),"") | AG31: =IFERROR(VLOOKUP(AF:AF,$B:$C,2,),"") | AI31: =IFERROR(VLOOKUP(AH:AH,$B:$C,2,),"")
A32: =A31+1 -> 27 | B32: AA9ZH1E2J | C32: 1U71S2SR2FA | D32: OU | E32: HN | F32: RN | H32: ABI0 | N32: AGIR | O32: ASI0 | Q32: No | R32: Mono SM+ | S32: Phase Out - ESAUIRTO | T32: 10 | U32: Catologue | W32: =IFERROR(VLOOKUP(V:V,$B:$C,2,),"") | Y32: =IFERROR(VLOOKUP(X:X,$B:$C,2,),"") | AA32: =IFERROR(VLOOKUP(Z:Z,$B:$C,2,),"") | AC32: =IFERROR(VLOOKUP(AB:AB,$B:$C,2,),"") | AE32: =IFERROR(VLOOKUP(AD:AD,$B:$C,2,),"") | AG32: =IFERROR(VLOOKUP(AF:AF,$B:$C,2,),"") | AI32: =IFERROR(VLOOKUP(AH:AH,$B:$C,2,),"")
A33: =A32+1 -> 28 | B33: AE1XY1E00 | C33: 1U71S2ST1FA | D33: OU | E33: HN | F33: RN | H33: ABI0 | N33: AGIR | O33: ASI0 | Q33: Yes | R33: Mono SM+ | S33: Sostituisce 1U71S2SR2FA | T33: 10 | U33: Catologue | W33: =IFERROR(VLOOKUP(V:V,$B:$C,2,),"") | Y33: =IFERROR(VLOOKUP(X:X,$B:$C,2,),"") | AA33: =IFERROR(VLOOKUP(Z:Z,$B:$C,2,),"") | AC33: =IFERROR(VLOOKUP(AB:AB,$B:$C,2,),"") | AE33: =IFERROR(VLOOKUP(AD:AD,$B:$C,2,),"") | AG33: =IFERROR(VLOOKUP(AF:AF,$B:$C,2,),"") | AI33: =IFERROR(VLOOKUP(AH:AH,$B:$C,2,),"")
A34: =A33+1 -> 29 | B34: AA9Z27E00 | C34: 1U105S2SS2FA | D34: OU | E34: HN | F34: RN | H34: ABI0 | N34: AGIR | O34: ASI0 | Q34: No | R34: Mono SM+ | S34: Phase Out - ESAUIRTO | T34: 5 | U34: LCAC | W34: =IFERROR(VLOOKUP(V:V,$B:$C,2,),"") | Y34: =IFERROR(VLOOKUP(X:X,$B:$C,2,),"") | AA34: =IFERROR(VLOOKUP(Z:Z,$B:$C,2,),"") | AC34: =IFERROR(VLOOKUP(AB:AB,$B:$C,2,),"") | AE34: =IFERROR(VLOOKUP(AD:AD,$B:$C,2,),"") | AG34: =IFERROR(VLOOKUP(AF:AF,$B:$C,2,),"") | AI34: =IFERROR(VLOOKUP(AH:AH,$B:$C,2,),"")
A35: =A34+1 -> 30 | B35: AE1XF6E00 | C35: 1U105S2SQ1FA | D35: OU | E35: HN | F35: RN | H35: ABI0 | N35: AGIR | O35: ASI0 | Q35: Yes | R35: Mono SM+ | S35: Sostituisce 1U105S2SS2FA | T35: 5 | U35: LCAC | W35: =IFERROR(VLOOKUP(V:V,$B:$C,2,),"") | Y35: =IFERROR(VLOOKUP(X:X,$B:$C,2,),"") | AA35: =IFERROR(VLOOKUP(Z:Z,$B:$C,2,),"") | AC35: =IFERROR(VLOOKUP(AB:AB,$B:$C,2,),"") | AE35: =IFERROR(VLOOKUP(AD:AD,$B:$C,2,),"") | AG35: =IFERROR(VLOOKUP(AF:AF,$B:$C,2,),"") | AI35: =IFERROR(VLOOKUP(AH:AH,$B:$C,2,),"")
A36: =A35+1 -> 31 | B36: AA9ZJ0E29 | C36: 1U105S2SS1FB | D36: OU | E36: HN | F36: RN | H36: ABI0 | N36: AGIR | O36: ASI0 | Q36: Yes | R36: Mono SM+ | S36: Three Phase | T36: 5 | U36: LCAC | W36: =IFERROR(VLOOKUP(V:V,$B:$C,2,),"") | Y36: =IFERROR(VLOOKUP(X:X,$B:$C,2,),"") | AA36: =IFERROR(VLOOKUP(Z:Z,$B:$C,2,),"") | AC36: =IFERROR(VLOOKUP(AB:AB,$B:$C,2,),"") | AE36: =IFERROR(VLOOKUP(AD:AD,$B:$C,2,),"") | AG36: =IFERROR(VLOOKUP(AF:AF,$B:$C,2,),"") | AI36: =IFERROR(VLOOKUP(AH:AH,$B:$C,2,),"")
A37: =A36+1 -> 32 | B37: AA9Z35E00 | C37: 1U125S2SN2FA | D37: OU | E37: HN | F37: RN | H37: ABI0 | N37: AGIR | O37: ASI0 | Q37: No | R37: Mono SM+ | S37: ESAUIRTO | T37: 5 | U37: LCAC | W37: =IFERROR(VLOOKUP(V:V,$B:$C,2,),"") | Y37: =IFERROR(VLOOKUP(X:X,$B:$C,2,),"") | AA37: =IFERROR(VLOOKUP(Z:Z,$B:$C,2,),"") | AC37: =IFERROR(VLOOKUP(AB:AB,$B:$C,2,),"") | AE37: =IFERROR(VLOOKUP(AD:AD,$B:$C,2,),"") | AG37: =IFERROR(VLOOKUP(AF:AF,$B:$C,2,),"") | AI37: =IFERROR(VLOOKUP(AH:AH,$B:$C,2,),"")
A38: =A37+1 -> 33 | B38: AE2182E00 | C38: 1U125S2SN3FA | D38: OU | E38: HN | F38: RN | H38: ABI0 | N38: AGIR | O38: ASI0 | Q38: Yes | R38: Mono SM+ | S38: Sostituisce 1U125S2SN2FA | T38: 5 | U38: LCAC | W38: =IFERROR(VLOOKUP(V:V,$B:$C,2,),"") | Y38: =IFERROR(VLOOKUP(X:X,$B:$C,2,),"") | AA38: =IFERROR(VLOOKUP(Z:Z,$B:$C,2,),"") | AC38: =IFERROR(VLOOKUP(AB:AB,$B:$C,2,),"") | AE38: =IFERROR(VLOOKUP(AD:AD,$B:$C,2,),"") | AG38: =IFERROR(VLOOKUP(AF:AF,$B:$C,2,),"") | AI38: =IFERROR(VLOOKUP(AH:AH,$B:$C,2,),"")
A39: =A38+1 -> 34 | B39: AA9Z38E00 | C39: 1U125S2SN2FB | D39: OU | E39: HN | F39: RN | H39: ABI0 | N39: AGIR | O39: ASI0 | Q39: Yes | R39: Mono SM+ | S39: Three Phase | T39: 5 | U39: LCAC | W39: =IFERROR(VLOOKUP(V:V,$B:$C,2,),"") | Y39: =IFERROR(VLOOKUP(X:X,$B:$C,2,),"") | AA39: =IFERROR(VLOOKUP(Z:Z,$B:$C,2,),"") | AC39: =IFERROR(VLOOKUP(AB:AB,$B:$C,2,),"") | AE39: =IFERROR(VLOOKUP(AD:AD,$B:$C,2,),"") | AG39: =IFERROR(VLOOKUP(AF:AF,$B:$C,2,),"") | AI39: =IFERROR(VLOOKUP(AH:AH,$B:$C,2,),"")
A40: =A39+1 -> 35 | B40: AE2181E00 | C40: 1U125S2SN3FB | D40: OU | E40: HN | F40: RN | H40: ABI0 | N40: AGIR | O40: ASI0 | Q40: No | R40: Mono SM+ | S40: Three Phase - New model 2026 | T40: 5 | U40: LCAC | W40: =IFERROR(VLOOKUP(V:V,$B:$C,2,),"") | Y40: =IFERROR(VLOOKUP(X:X,$B:$C,2,),"") | AA40: =IFERROR(VLOOKUP(Z:Z,$B:$C,2,),"") | AC40: =IFERROR(VLOOKUP(AB:AB,$B:$C,2,),"") | AE40: =IFERROR(VLOOKUP(AD:AD,$B:$C,2,),"") | AG40: =IFERROR(VLOOKUP(AF:AF,$B:$C,2,),"") | AI40: =IFERROR(VLOOKUP(AH:AH,$B:$C,2,),"")
A41: =A40+1 -> 36 | B41: AA9Z33E00 | C41: 1U140S2SN1FA | D41: OU | E41: HN | F41: RN | H41: ABI0 | N41: AGIR | O41: ASI0 | Q41: Yes | R41: Mono SM+ | S41: Phase out | T41: 5 | U41: LCAC | W41: =IFERROR(VLOOKUP(V:V,$B:$C,2,),"") | Y41: =IFERROR(VLOOKUP(X:X,$B:$C,2,),"") | AA41: =IFERROR(VLOOKUP(Z:Z,$B:$C,2,),"") | AC41: =IFERROR(VLOOKUP(AB:AB,$B:$C,2,),"") | AE41: =IFERROR(VLOOKUP(AD:AD,$B:$C,2,),"") | AG41: =IFERROR(VLOOKUP(AF:AF,$B:$C,2,),"") | AI41: =IFERROR(VLOOKUP(AH:AH,$B:$C,2,),"")
A42: =A41+1 -> 37 | B42: AE2183E00 | C42: 1U140S2SN2FA | D42: OU | E42: HN | F42: RN | H42: ABI0 | N42: AGIR | O42: ASI0 | Q42: No | R42: Mono SM+ | S42: New model 2026 | T42: 5 | U42: LCAC | W42: =IFERROR(VLOOKUP(V:V,$B:$C,2,),"") | Y42: =IFERROR(VLOOKUP(X:X,$B:$C,2,),"") | AA42: =IFERROR(VLOOKUP(Z:Z,$B:$C,2,),"") | AC42: =IFERROR(VLOOKUP(AB:AB,$B:$C,2,),"") | AE42: =IFERROR(VLOOKUP(AD:AD,$B:$C,2,),"") | AG42: =IFERROR(VLOOKUP(AF:AF,$B:$C,2,),"") | AI42: =IFERROR(VLOOKUP(AH:AH,$B:$C,2,),"")
A43: =A42+1 -> 38 | B43: AA9Z34E00 | C43: 1U140S2SN1FB | D43: OU | E43: HN | F43: RN | H43: ABI0 | N43: AGIR | O43: ASI0 | Q43: Yes | R43: Mono SM+ | S43: Three Phase phase out | T43: 5 | U43: LCAC | W43: =IFERROR(VLOOKUP(V:V,$B:$C,2,),"") | Y43: =IFERROR(VLOOKUP(X:X,$B:$C,2,),"") | AA43: =IFERROR(VLOOKUP(Z:Z,$B:$C,2,),"") | AC43: =IFERROR(VLOOKUP(AB:AB,$B:$C,2,),"") | AE43: =IFERROR(VLOOKUP(AD:AD,$B:$C,2,),"") | AG43: =IFERROR(VLOOKUP(AF:AF,$B:$C,2,),"") | AI43: =IFERROR(VLOOKUP(AH:AH,$B:$C,2,),"")
A44: =A43+1 -> 39 | B44: AE2180E00 | C44: 1U140S2SN2FB | D44: OU | E44: HN | F44: RN | H44: ABI0 | N44: AGIR | O44: ASI0 | Q44: No | R44: Mono SM+ | S44: Three Phase - New model 2026 | T44: 5 | U44: LCAC | W44: =IFERROR(VLOOKUP(V:V,$B:$C,2,),"") | Y44: =IFERROR(VLOOKUP(X:X,$B:$C,2,),"") | AA44: =IFERROR(VLOOKUP(Z:Z,$B:$C,2,),"") | AC44: =IFERROR(VLOOKUP(AB:AB,$B:$C,2,),"") | AE44: =IFERROR(VLOOKUP(AD:AD,$B:$C,2,),"") | AG44: =IFERROR(VLOOKUP(AF:AF,$B:$C,2,),"") | AI44: =IFERROR(VLOOKUP(AH:AH,$B:$C,2,),"")
A45: =A44+1 -> 40 | B45: AA9Z37E00 | C45: 1U140S2SP2FA | D45: OU | E45: HN | F45: RN | H45: ABI0 | N45: AGIR | O45: ASI0 | Q45: Yes | R45: Mono SM+ | T45: 5 | U45: LCAC | W45: =IFERROR(VLOOKUP(V:V,$B:$C,2,),"") | Y45: =IFERROR(VLOOKUP(X:X,$B:$C,2,),"") | AA45: =IFERROR(VLOOKUP(Z:Z,$B:$C,2,),"") | AC45: =IFERROR(VLOOKUP(AB:AB,$B:$C,2,),"") | AE45: =IFERROR(VLOOKUP(AD:AD,$B:$C,2,),"") | AG45: =IFERROR(VLOOKUP(AF:AF,$B:$C,2,),"") | AI45: =IFERROR(VLOOKUP(AH:AH,$B:$C,2,),"")
A46: =A45+1 -> 41 | B46: AA9Z36E00 | C46: 1U140S2SP2FB | D46: OU | E46: HN | F46: RN | H46: ABI0 | N46: AGIR | O46: ASI0 | Q46: Yes | R46: Mono SM+ | S46: Three Phase | T46: 5 | U46: LCAC | W46: =IFERROR(VLOOKUP(V:V,$B:$C,2,),"") | Y46: =IFERROR(VLOOKUP(X:X,$B:$C,2,),"") | AA46: =IFERROR(VLOOKUP(Z:Z,$B:$C,2,),"") | AC46: =IFERROR(VLOOKUP(AB:AB,$B:$C,2,),"") | AE46: =IFERROR(VLOOKUP(AD:AD,$B:$C,2,),"") | AG46: =IFERROR(VLOOKUP(AF:AF,$B:$C,2,),"") | AI46: =IFERROR(VLOOKUP(AH:AH,$B:$C,2,),"")
A47: =A46+1 -> 42 | B47: AA9Z73E00 | C47: 1U160S2SP1FB | D47: OU | E47: HN | F47: RN | H47: ABI0 | N47: AGIR | O47: ASI0 | Q47: Yes | R47: Mono SM+ | S47: Three Phase | T47: 5 | U47: LCAC | W47: =IFERROR(VLOOKUP(V:V,$B:$C,2,),"") | Y47: =IFERROR(VLOOKUP(X:X,$B:$C,2,),"") | AA47: =IFERROR(VLOOKUP(Z:Z,$B:$C,2,),"") | AC47: =IFERROR(VLOOKUP(AB:AB,$B:$C,2,),"") | AE47: =IFERROR(VLOOKUP(AD:AD,$B:$C,2,),"") | AG47: =IFERROR(VLOOKUP(AF:AF,$B:$C,2,),"") | AI47: =IFERROR(VLOOKUP(AH:AH,$B:$C,2,),"")
A48: =A47+1 -> 43 | B48: AA9WE2E29 | C48: 1UH200W1ERK | D48: OU | E48: HN | F48: RN | H48: ABI0 | N48: AGIR | O48: ASI0 | Q48: Yes | R48: Mono SM+ | T48: 5 | U48: LCAC | W48: =IFERROR(VLOOKUP(V:V,$B:$C,2,),"") | Y48: =IFERROR(VLOOKUP(X:X,$B:$C,2,),"") | AA48: =IFERROR(VLOOKUP(Z:Z,$B:$C,2,),"") | AC48: =IFERROR(VLOOKUP(AB:AB,$B:$C,2,),"") | AE48: =IFERROR(VLOOKUP(AD:AD,$B:$C,2,),"") | AG48: =IFERROR(VLOOKUP(AF:AF,$B:$C,2,),"") | AI48: =IFERROR(VLOOKUP(AH:AH,$B:$C,2,),"")
A49: =A48+1 -> 44 | B49: AA9WF0E29 | C49: 1UH250W1ERK | D49: OU | E49: HN | F49: RN | H49: ABI0 | N49: AGIR | O49: ASI0 | Q49: Yes | R49: Mono SM+ | T49: 5 | U49: LCAC | W49: =IFERROR(VLOOKUP(V:V,$B:$C,2,),"") | Y49: =IFERROR(VLOOKUP(X:X,$B:$C,2,),"") | AA49: =IFERROR(VLOOKUP(Z:Z,$B:$C,2,),"") | AC49: =IFERROR(VLOOKUP(AB:AB,$B:$C,2,),"") | AE49: =IFERROR(VLOOKUP(AD:AD,$B:$C,2,),"") | AG49: =IFERROR(VLOOKUP(AF:AF,$B:$C,2,),"") | AI49: =IFERROR(VLOOKUP(AH:AH,$B:$C,2,),"")
A50: =A49+1 -> 45 | E50: --- | F50: --- | W50: =IFERROR(VLOOKUP(V:V,$B:$C,2,),"") | Y50: =IFERROR(VLOOKUP(X:X,$B:$C,2,),"") | AA50: =IFERROR(VLOOKUP(Z:Z,$B:$C,2,),"") | AC50: =IFERROR(VLOOKUP(AB:AB,$B:$C,2,),"") | AE50: =IFERROR(VLOOKUP(AD:AD,$B:$C,2,),"") | AG50: =IFERROR(VLOOKUP(AF:AF,$B:$C,2,),"") | AI50: =IFERROR(VLOOKUP(AH:AH,$B:$C,2,),"")
A51: =A50+1 -> 46 | B51: AAB0S0E09 | C51: 2U40S2SM1FA | D51: OU | E51: HN | F51: RN | H51: ABI0 | M51: ACI0 | N51: AGIR | O51: ASI0 | Q51: Yes | R51: Multi SM+ 1:2 | T51: 100 | U51: Catologue | W51: =IFERROR(VLOOKUP(V:V,$B:$C,2,),"") | Y51: =IFERROR(VLOOKUP(X:X,$B:$C,2,),"") | AA51: =IFERROR(VLOOKUP(Z:Z,$B:$C,2,),"") | AC51: =IFERROR(VLOOKUP(AB:AB,$B:$C,2,),"") | AE51: =IFERROR(VLOOKUP(AD:AD,$B:$C,2,),"") | AG51: =IFERROR(VLOOKUP(AF:AF,$B:$C,2,),"") | AI51: =IFERROR(VLOOKUP(AH:AH,$B:$C,2,),"")
A52: =A51+1 -> 47 | B52: AAB0T0E00 | C52: 2U50S2SM1FA-3 | D52: OU | E52: HN | F52: RN | H52: ABI0 | M52: ACI0 | N52: AGIR | O52: ASI0 | Q52: Yes | R52: Multi SM+ 1:2 | T52: 100 | U52: Catologue | W52: =IFERROR(VLOOKUP(V:V,$B:$C,2,),"") | Y52: =IFERROR(VLOOKUP(X:X,$B:$C,2,),"") | AA52: =IFERROR(VLOOKUP(Z:Z,$B:$C,2,),"") | AC52: =IFERROR(VLOOKUP(AB:AB,$B:$C,2,),"") | AE52: =IFERROR(VLOOKUP(AD:AD,$B:$C,2,),"") | AG52: =IFERROR(VLOOKUP(AF:AF,$B:$C,2,),"") | AI52: =IFERROR(VLOOKUP(AH:AH,$B:$C,2,),"")
A53: =A52+1 -> 48 | B53: AAA2PJE00 | C53: 3U55S2SR5FA | D53: OU | E53: HN | F53: RN | H53: ABI0 | M53: ACI0 | N53: AGIR | O53: ASI0 | Q53: Yes | R53: Multi SM+ 1:3 | T53: 100 | U53: Catologue | W53: =IFERROR(VLOOKUP(V:V,$B:$C,2,),"") | Y53: =IFERROR(VLOOKUP(X:X,$B:$C,2,),"") | AA53: =IFERROR(VLOOKUP(Z:Z,$B:$C,2,),"") | AC53: =IFERROR(VLOOKUP(AB:AB,$B:$C,2,),"") | AE53: =IFERROR(VLOOKUP(AD:AD,$B:$C,2,),"") | AG53: =IFERROR(VLOOKUP(AF:AF,$B:$C,2,),"") | AI53: =IFERROR(VLOOKUP(AH:AH,$B:$C,2,),"")
A54: =A53+1 -> 49 | B54: AAA2PHE00 | C54: 3U70S2SR5FA | D54: OU | E54: HN | F54: RN | H54: ABI0 | N54: AGIR | O54: ASI0 | Q54: Yes | R54: Multi SM+ 1:3 | T54: 10 | U54: Catologue | W54: =IFERROR(VLOOKUP(V:V,$B:$C,2,),"") | Y54: =IFERROR(VLOOKUP(X:X,$B:$C,2,),"") | AA54: =IFERROR(VLOOKUP(Z:Z,$B:$C,2,),"") | AC54: =IFERROR(VLOOKUP(AB:AB,$B:$C,2,),"") | AE54: =IFERROR(VLOOKUP(AD:AD,$B:$C,2,),"") | AG54: =IFERROR(VLOOKUP(AF:AF,$B:$C,2,),"") | AI54: =IFERROR(VLOOKUP(AH:AH,$B:$C,2,),"")
A55: =A54+1 -> 50 | B55: AAA2R7E00 | C55: 4U75S2SR5FA | D55: OU | E55: HN | F55: RN | H55: ABI0 | N55: AGIR | O55: ASI0 | Q55: Yes | R55: Multi SM+ 1:4 | T55: 10 | U55: Catologue | W55: =IFERROR(VLOOKUP(V:V,$B:$C,2,),"") | Y55: =IFERROR(VLOOKUP(X:X,$B:$C,2,),"") | AA55: =IFERROR(VLOOKUP(Z:Z,$B:$C,2,),"") | AC55: =IFERROR(VLOOKUP(AB:AB,$B:$C,2,),"") | AE55: =IFERROR(VLOOKUP(AD:AD,$B:$C,2,),"") | AG55: =IFERROR(VLOOKUP(AF:AF,$B:$C,2,),"") | AI55: =IFERROR(VLOOKUP(AH:AH,$B:$C,2,),"")
A56: =A55+1 -> 51 | B56: AAA2R5E00 | C56: 4U85S2SR5FA | D56: OU | E56: HN | F56: RN | H56: ABI0 | N56: AGIR | O56: ASI0 | Q56: Yes | R56: Multi SM+ 1:4 | T56: 10 | U56: Catologue | W56: =IFERROR(VLOOKUP(V:V,$B:$C,2,),"") | Y56: =IFERROR(VLOOKUP(X:X,$B:$C,2,),"") | AA56: =IFERROR(VLOOKUP(Z:Z,$B:$C,2,),"") | AC56: =IFERROR(VLOOKUP(AB:AB,$B:$C,2,),"") | AE56: =IFERROR(VLOOKUP(AD:AD,$B:$C,2,),"") | AG56: =IFERROR(VLOOKUP(AF:AF,$B:$C,2,),"") | AI56: =IFERROR(VLOOKUP(AH:AH,$B:$C,2,),"")
A57: =A56+1 -> 52 | B57: AAA2R6E00 | C57: 5U90S2SS5FA | D57: OU | E57: HN | F57: RN | H57: ABI0 | N57: AGIR | O57: ASI0 | Q57: Yes | R57: Multi SM+ 1:5 | T57: 10 | U57: Catologue | W57: =IFERROR(VLOOKUP(V:V,$B:$C,2,),"") | Y57: =IFERROR(VLOOKUP(X:X,$B:$C,2,),"") | AA57: =IFERROR(VLOOKUP(Z:Z,$B:$C,2,),"") | AC57: =IFERROR(VLOOKUP(AB:AB,$B:$C,2,),"") | AE57: =IFERROR(VLOOKUP(AD:AD,$B:$C,2,),"") | AG57: =IFERROR(VLOOKUP(AF:AF,$B:$C,2,),"") | AI57: =IFERROR(VLOOKUP(AH:AH,$B:$C,2,),"")
A58: =A57+1 -> 53 | B58: AAA2R8E00 | C58: 5U105S2SS5FA | D58: OU | E58: HN | F58: RN | H58: ABI0 | N58: AGIR | O58: ASI0 | Q58: Yes | R58: Multi SM+ 1:5 | T58: 10 | U58: Catologue | W58: =IFERROR(VLOOKUP(V:V,$B:$C,2,),"") | Y58: =IFERROR(VLOOKUP(X:X,$B:$C,2,),"") | AA58: =IFERROR(VLOOKUP(Z:Z,$B:$C,2,),"") | AC58: =IFERROR(VLOOKUP(AB:AB,$B:$C,2,),"") | AE58: =IFERROR(VLOOKUP(AD:AD,$B:$C,2,),"") | AG58: =IFERROR(VLOOKUP(AF:AF,$B:$C,2,),"") | AI58: =IFERROR(VLOOKUP(AH:AH,$B:$C,2,),"")
A59: =A58+1 -> 54 | B59: AA9D74E00 | C59: 5U125S2SN1FA | D59: OU | E59: HN | F59: RN | H59: ABI0 | N59: AGIR | O59: ASI0 | Q59: Yes | R59: Multi SM+ 1:5 | T59: 10 | U59: Catologue | W59: =IFERROR(VLOOKUP(V:V,$B:$C,2,),"") | Y59: =IFERROR(VLOOKUP(X:X,$B:$C,2,),"") | AA59: =IFERROR(VLOOKUP(Z:Z,$B:$C,2,),"") | AC59: =IFERROR(VLOOKUP(AB:AB,$B:$C,2,),"") | AE59: =IFERROR(VLOOKUP(AD:AD,$B:$C,2,),"") | AG59: =IFERROR(VLOOKUP(AF:AF,$B:$C,2,),"") | AI59: =IFERROR(VLOOKUP(AH:AH,$B:$C,2,),"")
A60: =A59+1 -> 55 | E60: --- | F60: --- | W60: =IFERROR(VLOOKUP(V:V,$B:$C,2,),"") | Y60: =IFERROR(VLOOKUP(X:X,$B:$C,2,),"") | AA60: =IFERROR(VLOOKUP(Z:Z,$B:$C,2,),"") | AC60: =IFERROR(VLOOKUP(AB:AB,$B:$C,2,),"") | AE60: =IFERROR(VLOOKUP(AD:AD,$B:$C,2,),"") | AG60: =IFERROR(VLOOKUP(AF:AF,$B:$C,2,),"") | AI60: =IFERROR(VLOOKUP(AH:AH,$B:$C,2,),"")
A61: =A60+1 -> 56 | B61: AABQPAE00 | C61: AS20XCAHRA-MB | D61: IU | E61: HN | F61: RN | H61: ABI0 | J61: ABI3 | N61: AGIR | O61: ASI0 | Q61: Yes | R61: Expert Black Black | T61: 5 | U61: Catologue | W61: =IFERROR(VLOOKUP(V:V,$B:$C,2,),"") | Y61: =IFERROR(VLOOKUP(X:X,$B:$C,2,),"") | AA61: =IFERROR(VLOOKUP(Z:Z,$B:$C,2,),"") | AC61: =IFERROR(VLOOKUP(AB:AB,$B:$C,2,),"") | AE61: =IFERROR(VLOOKUP(AD:AD,$B:$C,2,),"") | AG61: =IFERROR(VLOOKUP(AF:AF,$B:$C,2,),"") | AI61: =IFERROR(VLOOKUP(AH:AH,$B:$C,2,),"")
A62: =A61+1 -> 57 | B62: AABQPBE00 | C62: AS25XCAHRA-MB | D62: IU | E62: HN | F62: RN | H62: ABI0 | J62: ABI3 | N62: AGIR | O62: ASI0 | Q62: Yes | R62: Expert Black Black | T62: 5 | U62: Catologue | W62: =IFERROR(VLOOKUP(V:V,$B:$C,2,),"") | Y62: =IFERROR(VLOOKUP(X:X,$B:$C,2,),"") | AA62: =IFERROR(VLOOKUP(Z:Z,$B:$C,2,),"") | AC62: =IFERROR(VLOOKUP(AB:AB,$B:$C,2,),"") | AE62: =IFERROR(VLOOKUP(AD:AD,$B:$C,2,),"") | AG62: =IFERROR(VLOOKUP(AF:AF,$B:$C,2,),"") | AI62: =IFERROR(VLOOKUP(AH:AH,$B:$C,2,),"")
A63: =A62+1 -> 58 | B63: AABQQ7E00 | C63: AS35XCAHRA-MB | D63: IU | E63: HN | F63: RN | H63: ABI0 | J63: ABI3 | N63: AGIR | O63: ASI0 | Q63: Yes | R63: Expert Black Black | T63: 5 | U63: Catologue | W63: =IFERROR(VLOOKUP(V:V,$B:$C,2,),"") | Y63: =IFERROR(VLOOKUP(X:X,$B:$C,2,),"") | AA63: =IFERROR(VLOOKUP(Z:Z,$B:$C,2,),"") | AC63: =IFERROR(VLOOKUP(AB:AB,$B:$C,2,),"") | AE63: =IFERROR(VLOOKUP(AD:AD,$B:$C,2,),"") | AG63: =IFERROR(VLOOKUP(AF:AF,$B:$C,2,),"") | AI63: =IFERROR(VLOOKUP(AH:AH,$B:$C,2,),"")
A64: =A63+1 -> 59 | B64: AABQR6E00 | C64: AS42XCAHRA-MB | D64: IU | E64: HN | H64: ABI0 | J64: ABI3 | O64: ASI0 | Q64: Yes | R64: Expert Black Black | S64: Phase Out - Clean Stock | T64: 5 | U64: Catologue | W64: =IFERROR(VLOOKUP(V:V,$B:$C,2,),"") | Y64: =IFERROR(VLOOKUP(X:X,$B:$C,2,),"") | AA64: =IFERROR(VLOOKUP(Z:Z,$B:$C,2,),"") | AC64: =IFERROR(VLOOKUP(AB:AB,$B:$C,2,),"") | AE64: =IFERROR(VLOOKUP(AD:AD,$B:$C,2,),"") | AG64: =IFERROR(VLOOKUP(AF:AF,$B:$C,2,),"") | AI64: =IFERROR(VLOOKUP(AH:AH,$B:$C,2,),"")
A65: =A64+1 -> 60 | B65: AABQQAE00 | C65: AS42XCAHRA-MB1 | D65: IU | E65: HN | F65: RN | H65: ABI0 | J65: ABI3 | N65: AGIR | O65: ASI0 | Q65: No | R65: Expert Black Black | S65: New model Sostituisce AS35XCAHRA-MB | T65: 5 | U65: Catologue | W65: =IFERROR(VLOOKUP(V:V,$B:$C,2,),"") | Y65: =IFERROR(VLOOKUP(X:X,$B:$C,2,),"") | AA65: =IFERROR(VLOOKUP(Z:Z,$B:$C,2,),"") | AC65: =IFERROR(VLOOKUP(AB:AB,$B:$C,2,),"") | AE65: =IFERROR(VLOOKUP(AD:AD,$B:$C,2,),"") | AG65: =IFERROR(VLOOKUP(AF:AF,$B:$C,2,),"") | AI65: =IFERROR(VLOOKUP(AH:AH,$B:$C,2,),"")
A66: =A65+1 -> 61 | B66: AABQR5E00 | C66: AS50XCAHRA-MB | D66: IU | E66: HN | F66: RN | H66: ABI0 | J66: ABI3 | N66: AGIR | O66: ASI0 | Q66: Yes | R66: Expert Black Black | T66: 5 | U66: Catologue | W66: =IFERROR(VLOOKUP(V:V,$B:$C,2,),"") | Y66: =IFERROR(VLOOKUP(X:X,$B:$C,2,),"") | AA66: =IFERROR(VLOOKUP(Z:Z,$B:$C,2,),"") | AC66: =IFERROR(VLOOKUP(AB:AB,$B:$C,2,),"") | AE66: =IFERROR(VLOOKUP(AD:AD,$B:$C,2,),"") | AG66: =IFERROR(VLOOKUP(AF:AF,$B:$C,2,),"") | AI66: =IFERROR(VLOOKUP(AH:AH,$B:$C,2,),"")
A67: =A66+1 -> 62 | B67: AAC101E00 | C67: AS71XCAHRA-MB | D67: IU | E67: HN | F67: RN | H67: ABI0 | N67: AGIR | O67: ASI0 | Q67: Yes | R67: Expert Black Black | T67: 5 | U67: Catologue | W67: =IFERROR(VLOOKUP(V:V,$B:$C,2,),"") | Y67: =IFERROR(VLOOKUP(X:X,$B:$C,2,),"") | AA67: =IFERROR(VLOOKUP(Z:Z,$B:$C,2,),"") | AC67: =IFERROR(VLOOKUP(AB:AB,$B:$C,2,),"") | AE67: =IFERROR(VLOOKUP(AD:AD,$B:$C,2,),"") | AG67: =IFERROR(VLOOKUP(AF:AF,$B:$C,2,),"") | AI67: =IFERROR(VLOOKUP(AH:AH,$B:$C,2,),"")
A68: =A67+1 -> 63 | E68: --- | F68: --- | W68: =IFERROR(VLOOKUP(V:V,$B:$C,2,),"") | Y68: =IFERROR(VLOOKUP(X:X,$B:$C,2,),"") | AA68: =IFERROR(VLOOKUP(Z:Z,$B:$C,2,),"") | AC68: =IFERROR(VLOOKUP(AB:AB,$B:$C,2,),"") | AE68: =IFERROR(VLOOKUP(AD:AD,$B:$C,2,),"") | AG68: =IFERROR(VLOOKUP(AF:AF,$B:$C,2,),"") | AI68: =IFERROR(VLOOKUP(AH:AH,$B:$C,2,),"")
A69: =A68+1 -> 64 | B69: AABQP1E00 | C69: AS20XCAHRA | D69: IU | E69: HN | F69: RN | H69: ABI0 | J69: ABI3 | N69: AGIR | O69: ASI0 | Q69: Yes | R69: Expert White | T69: 5 | U69: Catologue | W69: =IFERROR(VLOOKUP(V:V,$B:$C,2,),"") | Y69: =IFERROR(VLOOKUP(X:X,$B:$C,2,),"") | AA69: =IFERROR(VLOOKUP(Z:Z,$B:$C,2,),"") | AC69: =IFERROR(VLOOKUP(AB:AB,$B:$C,2,),"") | AE69: =IFERROR(VLOOKUP(AD:AD,$B:$C,2,),"") | AG69: =IFERROR(VLOOKUP(AF:AF,$B:$C,2,),"") | AI69: =IFERROR(VLOOKUP(AH:AH,$B:$C,2,),"")
A70: =A69+1 -> 65 | B70: AABQP0E00 | C70: AS25XCAHRA | D70: IU | E70: HN | F70: RN | H70: ABI0 | J70: ABI3 | N70: AGIR | O70: ASI0 | Q70: Yes | R70: Expert White | T70: 5 | U70: Catologue | W70: =IFERROR(VLOOKUP(V:V,$B:$C,2,),"") | Y70: =IFERROR(VLOOKUP(X:X,$B:$C,2,),"") | AA70: =IFERROR(VLOOKUP(Z:Z,$B:$C,2,),"") | AC70: =IFERROR(VLOOKUP(AB:AB,$B:$C,2,),"") | AE70: =IFERROR(VLOOKUP(AD:AD,$B:$C,2,),"") | AG70: =IFERROR(VLOOKUP(AF:AF,$B:$C,2,),"") | AI70: =IFERROR(VLOOKUP(AH:AH,$B:$C,2,),"")
A71: =A70+1 -> 66 | B71: AABQQ0E00 | C71: AS35XCAHRA | D71: IU | E71: HN | F71: RN | H71: ABI0 | J71: ABI3 | N71: AGIR | O71: ASI0 | Q71: Yes | R71: Expert White | T71: 5 | U71: Catologue | W71: =IFERROR(VLOOKUP(V:V,$B:$C,2,),"") | Y71: =IFERROR(VLOOKUP(X:X,$B:$C,2,),"") | AA71: =IFERROR(VLOOKUP(Z:Z,$B:$C,2,),"") | AC71: =IFERROR(VLOOKUP(AB:AB,$B:$C,2,),"") | AE71: =IFERROR(VLOOKUP(AD:AD,$B:$C,2,),"") | AG71: =IFERROR(VLOOKUP(AF:AF,$B:$C,2,),"") | AI71: =IFERROR(VLOOKUP(AH:AH,$B:$C,2,),"")
A72: =A71+1 -> 67 | B72: AABQR1E00 | C72: AS42XCAHRA | D72: IU | E72: HN | H72: ABI0 | J72: ABI3 | O72: ASI0 | Q72: No | R72: Expert White | S72: Phase Out - ESAUIRTO | T72: 5 | U72: Catologue | W72: =IFERROR(VLOOKUP(V:V,$B:$C,2,),"") | Y72: =IFERROR(VLOOKUP(X:X,$B:$C,2,),"") | AA72: =IFERROR(VLOOKUP(Z:Z,$B:$C,2,),"") | AC72: =IFERROR(VLOOKUP(AB:AB,$B:$C,2,),"") | AE72: =IFERROR(VLOOKUP(AD:AD,$B:$C,2,),"") | AG72: =IFERROR(VLOOKUP(AF:AF,$B:$C,2,),"") | AI72: =IFERROR(VLOOKUP(AH:AH,$B:$C,2,),"")
A73: =A72+1 -> 68 | B73: AABQQBE00 | C73: AS42XCAHRA-1 | D73: IU | E73: HN | F73: RN | H73: ABI0 | J73: ABI3 | N73: AGIR | O73: ASI0 | Q73: Yes | R73: Expert White | S73: Sostituisce AS42XCAHRA | T73: 5 | U73: Catologue | W73: =IFERROR(VLOOKUP(V:V,$B:$C,2,),"") | Y73: =IFERROR(VLOOKUP(X:X,$B:$C,2,),"") | AA73: =IFERROR(VLOOKUP(Z:Z,$B:$C,2,),"") | AC73: =IFERROR(VLOOKUP(AB:AB,$B:$C,2,),"") | AE73: =IFERROR(VLOOKUP(AD:AD,$B:$C,2,),"") | AG73: =IFERROR(VLOOKUP(AF:AF,$B:$C,2,),"") | AI73: =IFERROR(VLOOKUP(AH:AH,$B:$C,2,),"")
A74: =A73+1 -> 69 | B74: AABQR0E00 | C74: AS50XCAHRA | D74: IU | E74: HN | F74: RN | H74: ABI0 | J74: ABI3 | N74: AGIR | O74: ASI0 | Q74: Yes | R74: Expert White | T74: 5 | U74: Catologue | W74: =IFERROR(VLOOKUP(V:V,$B:$C,2,),"") | Y74: =IFERROR(VLOOKUP(X:X,$B:$C,2,),"") | AA74: =IFERROR(VLOOKUP(Z:Z,$B:$C,2,),"") | AC74: =IFERROR(VLOOKUP(AB:AB,$B:$C,2,),"") | AE74: =IFERROR(VLOOKUP(AD:AD,$B:$C,2,),"") | AG74: =IFERROR(VLOOKUP(AF:AF,$B:$C,2,),"") | AI74: =IFERROR(VLOOKUP(AH:AH,$B:$C,2,),"")
A75: =A74+1 -> 70 | B75: AAC100E00 | C75: AS71XCAHRA | D75: IU | E75: HN | F75: RN | H75: ABI0 | N75: AGIR | O75: ASI0 | Q75: Yes | R75: Expert White | T75: 5 | U75: Catologue | W75: =IFERROR(VLOOKUP(V:V,$B:$C,2,),"") | Y75: =IFERROR(VLOOKUP(X:X,$B:$C,2,),"") | AA75: =IFERROR(VLOOKUP(Z:Z,$B:$C,2,),"") | AC75: =IFERROR(VLOOKUP(AB:AB,$B:$C,2,),"") | AE75: =IFERROR(VLOOKUP(AD:AD,$B:$C,2,),"") | AG75: =IFERROR(VLOOKUP(AF:AF,$B:$C,2,),"") | AI75: =IFERROR(VLOOKUP(AH:AH,$B:$C,2,),"")
A76: =A75+1 -> 71 | E76: --- | F76: --- | W76: =IFERROR(VLOOKUP(V:V,$B:$C,2,),"") | Y76: =IFERROR(VLOOKUP(X:X,$B:$C,2,),"") | AA76: =IFERROR(VLOOKUP(Z:Z,$B:$C,2,),"") | AC76: =IFERROR(VLOOKUP(AB:AB,$B:$C,2,),"") | AE76: =IFERROR(VLOOKUP(AD:AD,$B:$C,2,),"") | AG76: =IFERROR(VLOOKUP(AF:AF,$B:$C,2,),"") | AI76: =IFERROR(VLOOKUP(AH:AH,$B:$C,2,),"")
A77: =A76+1 -> 72 | B77: AAA869E00 | C77: AS20S2SF1FA-MB3 | D77: IU | E77: HN | F77: RN | H77: ABI0 | J77: ABI3 | N77: AGIR | O77: ASI0 | Q77: Yes | R77: Flexis Black | T77: 5 | U77: Catologue | W77: =IFERROR(VLOOKUP(V:V,$B:$C,2,),"") | Y77: =IFERROR(VLOOKUP(X:X,$B:$C,2,),"") | AA77: =IFERROR(VLOOKUP(Z:Z,$B:$C,2,),"") | AC77: =IFERROR(VLOOKUP(AB:AB,$B:$C,2,),"") | AE77: =IFERROR(VLOOKUP(AD:AD,$B:$C,2,),"") | AG77: =IFERROR(VLOOKUP(AF:AF,$B:$C,2,),"") | AI77: =IFERROR(VLOOKUP(AH:AH,$B:$C,2,),"")
A78: =A77+1 -> 73 | B78: AAA86BE00 | C78: AS25S2SF1FA-MB3 | D78: IU | E78: HN | F78: RN | H78: ABI0 | J78: ABI3 | N78: AGIR | O78: ASI0 | Q78: Yes | R78: Flexis Black | T78: 5 | U78: Catologue | W78: =IFERROR(VLOOKUP(V:V,$B:$C,2,),"") | Y78: =IFERROR(VLOOKUP(X:X,$B:$C,2,),"") | AA78: =IFERROR(VLOOKUP(Z:Z,$B:$C,2,),"") | AC78: =IFERROR(VLOOKUP(AB:AB,$B:$C,2,),"") | AE78: =IFERROR(VLOOKUP(AD:AD,$B:$C,2,),"") | AG78: =IFERROR(VLOOKUP(AF:AF,$B:$C,2,),"") | AI78: =IFERROR(VLOOKUP(AH:AH,$B:$C,2,),"")
A79: =A78+1 -> 74 | B79: AAA6S9E00 | C79: AS35S2SF1FA-MB3 | D79: IU | E79: HN | F79: RN | H79: ABI0 | J79: ABI3 | N79: AGIR | O79: ASI0 | Q79: Yes | R79: Flexis Black | T79: 5 | U79: Catologue | W79: =IFERROR(VLOOKUP(V:V,$B:$C,2,),"") | Y79: =IFERROR(VLOOKUP(X:X,$B:$C,2,),"") | AA79: =IFERROR(VLOOKUP(Z:Z,$B:$C,2,),"") | AC79: =IFERROR(VLOOKUP(AB:AB,$B:$C,2,),"") | AE79: =IFERROR(VLOOKUP(AD:AD,$B:$C,2,),"") | AG79: =IFERROR(VLOOKUP(AF:AF,$B:$C,2,),"") | AI79: =IFERROR(VLOOKUP(AH:AH,$B:$C,2,),"")
A80: =A79+1 -> 75 | B80: AAAYW1E00 | C80: AS42S2SF1FA-MB3 | D80: IU | E80: HN | F80: RN | H80: ABI0 | J80: ABI3 | N80: AGIR | O80: ASI0 | Q80: Yes | R80: Flexis Black | T80: 5 | U80: Catologue | W80: =IFERROR(VLOOKUP(V:V,$B:$C,2,),"") | Y80: =IFERROR(VLOOKUP(X:X,$B:$C,2,),"") | AA80: =IFERROR(VLOOKUP(Z:Z,$B:$C,2,),"") | AC80: =IFERROR(VLOOKUP(AB:AB,$B:$C,2,),"") | AE80: =IFERROR(VLOOKUP(AD:AD,$B:$C,2,),"") | AG80: =IFERROR(VLOOKUP(AF:AF,$B:$C,2,),"") | AI80: =IFERROR(VLOOKUP(AH:AH,$B:$C,2,),"")
A81: =A80+1 -> 76 | B81: AAACL8E00 | C81: AS50S2SF1FA-MB3 | D81: IU | E81: HN | F81: RN | H81: ABI0 | J81: ABI3 | N81: AGIR | O81: ASI0 | Q81: Yes | R81: Flexis Black | T81: 5 | U81: Catologue | W81: =IFERROR(VLOOKUP(V:V,$B:$C,2,),"") | Y81: =IFERROR(VLOOKUP(X:X,$B:$C,2,),"") | AA81: =IFERROR(VLOOKUP(Z:Z,$B:$C,2,),"") | AC81: =IFERROR(VLOOKUP(AB:AB,$B:$C,2,),"") | AE81: =IFERROR(VLOOKUP(AD:AD,$B:$C,2,),"") | AG81: =IFERROR(VLOOKUP(AF:AF,$B:$C,2,),"") | AI81: =IFERROR(VLOOKUP(AH:AH,$B:$C,2,),"")
A82: =A81+1 -> 77 | B82: AAACM9E00 | C82: AS71S2SF1FA-MB3 | D82: IU | E82: HN | F82: RN | H82: ABI0 | N82: AGIR | O82: ASI0 | Q82: Yes | R82: Flexis Black | T82: 5 | U82: Catologue | W82: =IFERROR(VLOOKUP(V:V,$B:$C,2,),"") | Y82: =IFERROR(VLOOKUP(X:X,$B:$C,2,),"") | AA82: =IFERROR(VLOOKUP(Z:Z,$B:$C,2,),"") | AC82: =IFERROR(VLOOKUP(AB:AB,$B:$C,2,),"") | AE82: =IFERROR(VLOOKUP(AD:AD,$B:$C,2,),"") | AG82: =IFERROR(VLOOKUP(AF:AF,$B:$C,2,),"") | AI82: =IFERROR(VLOOKUP(AH:AH,$B:$C,2,),"")
A83: =A82+1 -> 78 | E83: --- | F83: --- | W83: =IFERROR(VLOOKUP(V:V,$B:$C,2,),"") | Y83: =IFERROR(VLOOKUP(X:X,$B:$C,2,),"") | AA83: =IFERROR(VLOOKUP(Z:Z,$B:$C,2,),"") | AC83: =IFERROR(VLOOKUP(AB:AB,$B:$C,2,),"") | AE83: =IFERROR(VLOOKUP(AD:AD,$B:$C,2,),"") | AG83: =IFERROR(VLOOKUP(AF:AF,$B:$C,2,),"") | AI83: =IFERROR(VLOOKUP(AH:AH,$B:$C,2,),"")
A84: =A83+1 -> 79 | B84: AAA86AE00 | C84: AS20S2SF1FA-MW3 | D84: IU | E84: HN | F84: RN | H84: ABI0 | J84: ABI3 | N84: AGIR | O84: ASI0 | Q84: Yes | R84: Flexis White | T84: 5 | U84: Catologue | W84: =IFERROR(VLOOKUP(V:V,$B:$C,2,),"") | Y84: =IFERROR(VLOOKUP(X:X,$B:$C,2,),"") | AA84: =IFERROR(VLOOKUP(Z:Z,$B:$C,2,),"") | AC84: =IFERROR(VLOOKUP(AB:AB,$B:$C,2,),"") | AE84: =IFERROR(VLOOKUP(AD:AD,$B:$C,2,),"") | AG84: =IFERROR(VLOOKUP(AF:AF,$B:$C,2,),"") | AI84: =IFERROR(VLOOKUP(AH:AH,$B:$C,2,),"")
A85: =A84+1 -> 80 | B85: AAA86CE00 | C85: AS25S2SF1FA-MW3 | D85: IU | E85: HN | F85: RN | H85: ABI0 | J85: ABI3 | N85: AGIR | O85: ASI0 | Q85: Yes | R85: Flexis White | T85: 5 | U85: Catologue | W85: =IFERROR(VLOOKUP(V:V,$B:$C,2,),"") | Y85: =IFERROR(VLOOKUP(X:X,$B:$C,2,),"") | AA85: =IFERROR(VLOOKUP(Z:Z,$B:$C,2,),"") | AC85: =IFERROR(VLOOKUP(AB:AB,$B:$C,2,),"") | AE85: =IFERROR(VLOOKUP(AD:AD,$B:$C,2,),"") | AG85: =IFERROR(VLOOKUP(AF:AF,$B:$C,2,),"") | AI85: =IFERROR(VLOOKUP(AH:AH,$B:$C,2,),"")
A86: =A85+1 -> 81 | B86: AAA6S8E00 | C86: AS35S2SF1FA-MW3 | D86: IU | E86: HN | F86: RN | H86: ABI0 | J86: ABI3 | N86: AGIR | O86: ASI0 | Q86: Yes | R86: Flexis White | T86: 5 | U86: Catologue | W86: =IFERROR(VLOOKUP(V:V,$B:$C,2,),"") | Y86: =IFERROR(VLOOKUP(X:X,$B:$C,2,),"") | AA86: =IFERROR(VLOOKUP(Z:Z,$B:$C,2,),"") | AC86: =IFERROR(VLOOKUP(AB:AB,$B:$C,2,),"") | AE86: =IFERROR(VLOOKUP(AD:AD,$B:$C,2,),"") | AG86: =IFERROR(VLOOKUP(AF:AF,$B:$C,2,),"") | AI86: =IFERROR(VLOOKUP(AH:AH,$B:$C,2,),"")
A87: =A86+1 -> 82 | B87: AAAYW2E00 | C87: AS42S2SF1FA-MW3 | D87: IU | E87: HN | F87: RN | H87: ABI0 | J87: ABI3 | N87: AGIR | O87: ASI0 | Q87: Yes | R87: Flexis White | T87: 5 | U87: Catologue | W87: =IFERROR(VLOOKUP(V:V,$B:$C,2,),"") | Y87: =IFERROR(VLOOKUP(X:X,$B:$C,2,),"") | AA87: =IFERROR(VLOOKUP(Z:Z,$B:$C,2,),"") | AC87: =IFERROR(VLOOKUP(AB:AB,$B:$C,2,),"") | AE87: =IFERROR(VLOOKUP(AD:AD,$B:$C,2,),"") | AG87: =IFERROR(VLOOKUP(AF:AF,$B:$C,2,),"") | AI87: =IFERROR(VLOOKUP(AH:AH,$B:$C,2,),"")
A88: =A87+1 -> 83 | B88: AAACL9E00 | C88: AS50S2SF1FA-MW3 | D88: IU | E88: HN | F88: RN | H88: ABI0 | J88: ABI3 | N88: AGIR | O88: ASI0 | Q88: Yes | R88: Flexis White | T88: 5 | U88: Catologue | W88: =IFERROR(VLOOKUP(V:V,$B:$C,2,),"") | Y88: =IFERROR(VLOOKUP(X:X,$B:$C,2,),"") | AA88: =IFERROR(VLOOKUP(Z:Z,$B:$C,2,),"") | AC88: =IFERROR(VLOOKUP(AB:AB,$B:$C,2,),"") | AE88: =IFERROR(VLOOKUP(AD:AD,$B:$C,2,),"") | AG88: =IFERROR(VLOOKUP(AF:AF,$B:$C,2,),"") | AI88: =IFERROR(VLOOKUP(AH:AH,$B:$C,2,),"")
A89: =A88+1 -> 84 | B89: AAACM8E00 | C89: AS71S2SF1FA-MW3 | D89: IU | E89: HN | F89: RN | H89: ABI0 | N89: AGIR | O89: ASI0 | Q89: Yes | R89: Flexis White | T89: 5 | U89: Catologue | W89: =IFERROR(VLOOKUP(V:V,$B:$C,2,),"") | Y89: =IFERROR(VLOOKUP(X:X,$B:$C,2,),"") | AA89: =IFERROR(VLOOKUP(Z:Z,$B:$C,2,),"") | AC89: =IFERROR(VLOOKUP(AB:AB,$B:$C,2,),"") | AE89: =IFERROR(VLOOKUP(AD:AD,$B:$C,2,),"") | AG89: =IFERROR(VLOOKUP(AF:AF,$B:$C,2,),"") | AI89: =IFERROR(VLOOKUP(AH:AH,$B:$C,2,),"")
A90: =A89+1 -> 85 | B90: AAAVD0E00 | C90: AS105S2SF2FA-2 | D90: IU | E90: HN | F90: RN | H90: ABI0 | N90: AGIR | O90: ASI0 | Q90: Yes | R90: IES | T90: 5 | U90: LCAC | W90: =IFERROR(VLOOKUP(V:V,$B:$C,2,),"") | Y90: =IFERROR(VLOOKUP(X:X,$B:$C,2,),"") | AA90: =IFERROR(VLOOKUP(Z:Z,$B:$C,2,),"") | AC90: =IFERROR(VLOOKUP(AB:AB,$B:$C,2,),"") | AE90: =IFERROR(VLOOKUP(AD:AD,$B:$C,2,),"") | AG90: =IFERROR(VLOOKUP(AF:AF,$B:$C,2,),"") | AI90: =IFERROR(VLOOKUP(AH:AH,$B:$C,2,),"")
A91: =A90+1 -> 86 | E91: --- | F91: --- | W91: =IFERROR(VLOOKUP(V:V,$B:$C,2,),"") | Y91: =IFERROR(VLOOKUP(X:X,$B:$C,2,),"") | AA91: =IFERROR(VLOOKUP(Z:Z,$B:$C,2,),"") | AC91: =IFERROR(VLOOKUP(AB:AB,$B:$C,2,),"") | AE91: =IFERROR(VLOOKUP(AD:AD,$B:$C,2,),"") | AG91: =IFERROR(VLOOKUP(AF:AF,$B:$C,2,),"") | AI91: =IFERROR(VLOOKUP(AH:AH,$B:$C,2,),"")
A92: =A91+1 -> 87 | B92: AABF12E00 | C92: AS20PBAHRA | D92: IU | E92: HN | F92: RN | H92: ABI0 | N92: AGIR | O92: ASI0 | Q92: Yes | R92: Pearl | S92: Phase Out - Clean Stock | T92: 0 | U92: Catologue | W92: =IFERROR(VLOOKUP(V:V,$B:$C,2,),"") | Y92: =IFERROR(VLOOKUP(X:X,$B:$C,2,),"") | AA92: =IFERROR(VLOOKUP(Z:Z,$B:$C,2,),"") | AC92: =IFERROR(VLOOKUP(AB:AB,$B:$C,2,),"") | AE92: =IFERROR(VLOOKUP(AD:AD,$B:$C,2,),"") | AG92: =IFERROR(VLOOKUP(AF:AF,$B:$C,2,),"") | AI92: =IFERROR(VLOOKUP(AH:AH,$B:$C,2,),"")
A93: =A92+1 -> 88 | B93: AABF10E00 | C93: AS25PBAHRA | D93: IU | E93: HN | F93: RN | H93: ABI0 | N93: AGIR | O93: ASI0 | Q93: Yes | R93: Pearl | S93: Phase Out - Clean Stock | T93: 0 | U93: Catologue | W93: =IFERROR(VLOOKUP(V:V,$B:$C,2,),"") | Y93: =IFERROR(VLOOKUP(X:X,$B:$C,2,),"") | AA93: =IFERROR(VLOOKUP(Z:Z,$B:$C,2,),"") | AC93: =IFERROR(VLOOKUP(AB:AB,$B:$C,2,),"") | AE93: =IFERROR(VLOOKUP(AD:AD,$B:$C,2,),"") | AG93: =IFERROR(VLOOKUP(AF:AF,$B:$C,2,),"") | AI93: =IFERROR(VLOOKUP(AH:AH,$B:$C,2,),"")
A94: =A93+1 -> 89 | B94: AABF30E00 | C94: AS35PBAHRA | D94: IU | E94: HN | F94: RN | H94: ABI0 | N94: AGIR | O94: ASI0 | Q94: Yes | R94: Pearl | S94: Phase Out - Clean Stock | T94: 0 | U94: Catologue | W94: =IFERROR(VLOOKUP(V:V,$B:$C,2,),"") | Y94: =IFERROR(VLOOKUP(X:X,$B:$C,2,),"") | AA94: =IFERROR(VLOOKUP(Z:Z,$B:$C,2,),"") | AC94: =IFERROR(VLOOKUP(AB:AB,$B:$C,2,),"") | AE94: =IFERROR(VLOOKUP(AD:AD,$B:$C,2,),"") | AG94: =IFERROR(VLOOKUP(AF:AF,$B:$C,2,),"") | AI94: =IFERROR(VLOOKUP(AH:AH,$B:$C,2,),"")
A95: =A94+1 -> 90 | B95: AABF23E00 | C95: 1U25YEGFRA-1 | D95: OU | E95: HN | F95: RN | H95: ABI0 | N95: AGIR | O95: ASI0 | Q95: Yes | R95: Pearl | S95: Phase Out - Clean Stock | T95: 0 | U95: Catologue | W95: =IFERROR(VLOOKUP(V:V,$B:$C,2,),"") | Y95: =IFERROR(VLOOKUP(X:X,$B:$C,2,),"") | AA95: =IFERROR(VLOOKUP(Z:Z,$B:$C,2,),"") | AC95: =IFERROR(VLOOKUP(AB:AB,$B:$C,2,),"") | AE95: =IFERROR(VLOOKUP(AD:AD,$B:$C,2,),"") | AG95: =IFERROR(VLOOKUP(AF:AF,$B:$C,2,),"") | AI95: =IFERROR(VLOOKUP(AH:AH,$B:$C,2,),"")
A96: =A95+1 -> 91 | B96: AABF46E00 | C96: 1U35YEGFRA-1 | D96: OU | E96: HN | F96: RN | H96: ABI0 | N96: AGIR | O96: ASI0 | Q96: Yes | R96: Pearl | S96: Phase Out - Clean Stock | T96: 0 | U96: Catologue | W96: =IFERROR(VLOOKUP(V:V,$B:$C,2,),"") | Y96: =IFERROR(VLOOKUP(X:X,$B:$C,2,),"") | AA96: =IFERROR(VLOOKUP(Z:Z,$B:$C,2,),"") | AC96: =IFERROR(VLOOKUP(AB:AB,$B:$C,2,),"") | AE96: =IFERROR(VLOOKUP(AD:AD,$B:$C,2,),"") | AG96: =IFERROR(VLOOKUP(AF:AF,$B:$C,2,),"") | AI96: =IFERROR(VLOOKUP(AH:AH,$B:$C,2,),"")
A97: =A96+1 -> 92 | E97: --- | F97: --- | W97: =IFERROR(VLOOKUP(V:V,$B:$C,2,),"") | Y97: =IFERROR(VLOOKUP(X:X,$B:$C,2,),"") | AA97: =IFERROR(VLOOKUP(Z:Z,$B:$C,2,),"") | AC97: =IFERROR(VLOOKUP(AB:AB,$B:$C,2,),"") | AE97: =IFERROR(VLOOKUP(AD:AD,$B:$C,2,),"") | AG97: =IFERROR(VLOOKUP(AF:AF,$B:$C,2,),"") | AI97: =IFERROR(VLOOKUP(AH:AH,$B:$C,2,),"")
A98: =A97+1 -> 93 | B98: AACCXAE00 | C98: AS20PBAHRA-PRE | D98: IU | E98: HN | F98: RN | H98: ABI0 | J98: ABI3 | N98: AGIR | O98: ASI0 | Q98: Yes | R98: Pearl | T98: 50 | U98: Catologue | W98: =IFERROR(VLOOKUP(V:V,$B:$C,2,),"") | Y98: =IFERROR(VLOOKUP(X:X,$B:$C,2,),"") | AA98: =IFERROR(VLOOKUP(Z:Z,$B:$C,2,),"") | AC98: =IFERROR(VLOOKUP(AB:AB,$B:$C,2,),"") | AE98: =IFERROR(VLOOKUP(AD:AD,$B:$C,2,),"") | AG98: =IFERROR(VLOOKUP(AF:AF,$B:$C,2,),"") | AI98: =IFERROR(VLOOKUP(AH:AH,$B:$C,2,),"")
A99: =A98+1 -> 94 | B99: AACCX0E00 | C99: AS25PBPHRA-PRE | D99: IU | E99: HN | F99: RN | H99: ABI0 | J99: ABI3 | N99: AGIR | O99: ASI0 | Q99: Yes | R99: Pearl | T99: 150 | U99: Catologue | W99: =IFERROR(VLOOKUP(V:V,$B:$C,2,),"") | Y99: =IFERROR(VLOOKUP(X:X,$B:$C,2,),"") | AA99: =IFERROR(VLOOKUP(Z:Z,$B:$C,2,),"") | AC99: =IFERROR(VLOOKUP(AB:AB,$B:$C,2,),"") | AE99: =IFERROR(VLOOKUP(AD:AD,$B:$C,2,),"") | AG99: =IFERROR(VLOOKUP(AF:AF,$B:$C,2,),"") | AI99: =IFERROR(VLOOKUP(AH:AH,$B:$C,2,),"")
A100: =A99+1 -> 95 | B100: AACCY0E00 | C100: AS35PBPHRA-PRE | D100: IU | E100: HN | F100: RN | H100: ABI0 | J100: ABI3 | N100: AGIR | O100: ASI0 | Q100: Yes | R100: Pearl | T100: 150 | U100: Catologue | W100: =IFERROR(VLOOKUP(V:V,$B:$C,2,),"") | Y100: =IFERROR(VLOOKUP(X:X,$B:$C,2,),"") | AA100: =IFERROR(VLOOKUP(Z:Z,$B:$C,2,),"") | AC100: =IFERROR(VLOOKUP(AB:AB,$B:$C,2,),"") | AE100: =IFERROR(VLOOKUP(AD:AD,$B:$C,2,),"") | AG100: =IFERROR(VLOOKUP(AF:AF,$B:$C,2,),"") | AI100: =IFERROR(VLOOKUP(AH:AH,$B:$C,2,),"")
...

Sheet Tabella Traslata
B1: 2 | C1: 3 | D1: 4 | G1: 17 | H1: 18 | I1: 19 | J1: 20 | K1: 21 | N1: 36 | O1: 37 | P1: 38 | Q1: 39 | R1: 40 | S1: 41 | T1: 42 | U1: 43 | V1: 5 | W1: 6 | X1: 7 | Y1: 8 | Z1: 9 | AA1: 10 | AB1: 11 | AC1: 12 | AD1: 13 | AE1: 14 | AF1: 15 | AG1: 16 | AH1: 22 | AI1: 24 | AJ1: 26 | AK1: 28 | AL1: 30 | AM1: 32 | AN1: 34
A2: ID | B2: =VLOOKUP($A:$A,'Matrice Visualizzazione File 1'!$A:$AR,B$1,) -> Material | C2: =VLOOKUP($A:$A,'Matrice Visualizzazione File 1'!$A:$AR,C$1,) -> Model | D2: =VLOOKUP($A:$A,'Matrice Visualizzazione File 1'!$A:$AR,D$1,) -> Unit type | G2: =VLOOKUP($A:$A,'Matrice Visualizzazione File 1'!$A:$AR,G$1,) -> InCatalog | H2: =VLOOKUP($A:$A,'Matrice Visualizzazione File 1'!$A:$AR,H$1,) -> Nota Descritiva | I2: =VLOOKUP($A:$A,'Matrice Visualizzazione File 1'!$A:$AR,I$1,) -> Note Aggiuntive | J2: =VLOOKUP($A:$A,'Matrice Visualizzazione File 1'!$A:$AR,J$1,) -> Min Q.tà | K2: =VLOOKUP($A:$A,'Matrice Visualizzazione File 1'!$A:$AR,K$1,) -> Area | N2: =VLOOKUP($A:$A,'Matrice Visualizzazione File 1'!$A:$AR,N$1,) -> Famiglia | O2: =VLOOKUP($A:$A,'Matrice Visualizzazione File 1'!$A:$AR,O$1,) -> Tipologia | P2: =VLOOKUP($A:$A,'Matrice Visualizzazione File 1'!$A:$AR,P$1,) -> Tecnologia | Q2: =VLOOKUP($A:$A,'Matrice Visualizzazione File 1'!$A:$AR,Q$1,) -> Catalogo | R2: =VLOOKUP($A:$A,'Matrice Visualizzazione File 1'!$A:$AR,R$1,) -> Dimensionali | S2: =VLOOKUP($A:$A,'Matrice Visualizzazione File 1'!$A:$AR,S$1,) -> Scheda Tecnica | T2: =VLOOKUP($A:$A,'Matrice Visualizzazione File 1'!$A:$AR,T$1,) -> Descrizione Capitolato | U2: =VLOOKUP($A:$A,'Matrice Visualizzazione File 1'!$A:$AR,U$1,) -> Descrizione Capitolato Opzionale | ... AN2: =VLOOKUP($A:$A,'Matrice Visualizzazione File 1'!$A:$AR,AN$1,) -> Accessorio 5
A3: Tabella da non Toccare si aggiorna in automatico
V4: Colonne di appoggio per la matrice
A5: ID | B5: Material | C5: Model | D5: Unit type | E5: SalesArea | F5: Sale office | G5: InCatalog | H5: Nota Descritiva | I5: Note Aggiuntive | J5: Min Q.tà | K5: Area | L5: Avviamenti | M5: Accessori | N5: Famiglia | O5: Tipologia | P5: Tecnologia | Q5: Catalogo | R5: Dimensionali | S5: Scheda Tecnica | T5: Descrizione Capitolato | U5: Descrizione Capitolato Opzionale | V5: HN | W5: RN | X5: CN | Y5: Sale office 1 | Z5: Sale Office 2 | AA5: Sale office 3 | AB5: Sale office 4 | AC5: Sale office 5 | AD5: Sale office 6 | AE5: Sale office 7 | AF5: Sale office 8 | AG5: Sale office 9 | AH5: Codice Avviamento 1 | AI5: Codice Avviamento 2 | AJ5: Accessorio 1 | AK5: Accessorio 2 | AL5: Accessorio 3 | AM5: Accessorio 4 | AN5: Accessorio 5
A6: 1 | B6: =IFERROR(VLOOKUP($A:$A,'Matrice Visualizzazione File 1'!$A:$AR,B$1,),"") -> AB97Y0E00 | C6: =IFERROR(VLOOKUP($A:$A,'Matrice Visualizzazione File 1'!$A:$AR,C$1,),"") -> AP71DFMHRA DIZUN | D6: =IFERROR(VLOOKUP($A:$A,'Matrice Visualizzazione File 1'!$A:$AR,D$1,),"") -> IU | E6: =_xlfn.TEXTJOIN("|",TRUE,Tabella_Traslata[[#This Row],[HN]:[CN]]) -> HN|RN | F6: =_xlfn.TEXTJOIN("|",TRUE,Tabella_Traslata[[#This Row],[Sale office 1]:[Sale office 9]]) -> ABI0|AGIR|ASI0 | G6: =IFERROR(VLOOKUP($A:$A,'Matrice Visualizzazione File 1'!$A:$AR,G$1,),"") -> Yes | H6: =IFERROR(VLOOKUP($A:$A,'Matrice Visualizzazione File 1'!$A:$AR,H$1,),"") -> Cabinet | I6: =IFERROR(VLOOKUP($A:$A,'Matrice Visualizzazione File 1'!$A:$AR,I$1,),"") -> 0 | J6: =IFERROR(VLOOKUP($A:$A,'Matrice Visualizzazione File 1'!$A:$AR,J$1,),"") -> 5 | K6: =IFERROR(VLOOKUP($A:$A,'Matrice Visualizzazione File 1'!$A:$AR,K$1,),"") -> Catologue | L6: =_xlfn.TEXTJOIN("|",TRUE,Tabella_Traslata[[#This Row],[Codice Avviamento 1]:[Codice Avviamento 2]]) | M6: =_xlfn.TEXTJOIN("|",TRUE,Tabella_Traslata[[#This Row],[Accessorio 1]:[Accessorio 5]]) | N6: =IFERROR(VLOOKUP($A:$A,'Matrice Visualizzazione File 1'!$A:$AR,N$1,),"") | O6: =IFERROR(VLOOKUP($A:$A,'Matrice Visualizzazione File 1'!$A:$AR,O$1,),"") | P6: =IFERROR(VLOOKUP($A:$A,'Matrice Visualizzazione File 1'!$A:$AR,P$1,),"") | Q6: =IFERROR(VLOOKUP($A:$A,'Matrice Visualizzazione File 1'!$A:$AR,Q$1,),"") | R6: =IFERROR(VLOOKUP($A:$A,'Matrice Visualizzazione File 1'!$A:$AR,R$1,),"") | S6: =IFERROR(VLOOKUP($A:$A,'Matrice Visualizzazione File 1'!$A:$AR,S$1,),"") -> 0 | T6: =IFERROR(VLOOKUP($A:$A,'Matrice Visualizzazione File 1'!$A:$AR,T$1,),"") | U6: =IFERROR(VLOOKUP($A:$A,'Matrice Visualizzazione File 1'!$A:$AR,U$1,),"") | V6: =IF(IFERROR(VLOOKUP($A:$A,'Matrice Visualizzazione File 1'!$A:$AR,V$1,),"")=0,"",IFERROR(VLOOKUP($A:$A,'Matrice Visualizzazione File 1'!$A:$AR,V$1,),"")) -> HN | W6: =IF(IFERROR(VLOOKUP($A:$A,'Matrice Visualizzazione File 1'!$A:$AR,W$1,),"")=0,"",IFERROR(VLOOKUP($A:$A,'Matrice Visualizzazione File 1'!$A:$AR,W$1,),"")) -> RN | X6: =IF(IFERROR(VLOOKUP($A:$A,'Matrice Visualizzazione File 1'!$A:$AR,X$1,),"")=0,"",IFERROR(VLOOKUP($A:$A,'Matrice Visualizzazione File 1'!$A:$AR,X$1,),"")) | Y6: =IF(IFERROR(VLOOKUP($A:$A,'Matrice Visualizzazione File 1'!$A:$AR,Y$1,),"")=0,"",IFERROR(VLOOKUP($A:$A,'Matrice Visualizzazione File 1'!$A:$AR,Y$1,),"")) -> ABI0 | Z6: =IF(IFERROR(VLOOKUP($A:$A,'Matrice Visualizzazione File 1'!$A:$AR,Z$1,),"")=0,"",IFERROR(VLOOKUP($A:$A,'Matrice Visualizzazione File 1'!$A:$AR,Z$1,),"")) | AA6: =IF(IFERROR(VLOOKUP($A:$A,'Matrice Visualizzazione File 1'!$A:$AR,AA$1,),"")=0,"",IFERROR(VLOOKUP($A:$A,'Matrice Visualizzazione File 1'!$A:$AR,AA$1,),"")) | AB6: =IF(IFERROR(VLOOKUP($A:$A,'Matrice Visualizzazione File 1'!$A:$AR,AB$1,),"")=0,"",IFERROR(VLOOKUP($A:$A,'Matrice Visualizzazione File 1'!$A:$AR,AB$1,),"")) | AC6: =IF(IFERROR(VLOOKUP($A:$A,'Matrice Visualizzazione File 1'!$A:$AR,AC$1,),"")=0,"",IFERROR(VLOOKUP($A:$A,'Matrice Visualizzazione File 1'!$A:$AR,AC$1,),"")) | ... AN6: =IF(IFERROR(VLOOKUP($A:$A,'Matrice Visualizzazione File 1'!$A:$AR,AN$1,),"")=0,"",IFERROR(VLOOKUP($A:$A,'Matrice Visualizzazione File 1'!$A:$AR,AN$1,),""))
A7: =A6+1 -> 2 | B7: =IFERROR(VLOOKUP($A:$A,'Matrice Visualizzazione File 1'!$A:$AR,B$1,),"") -> AACKF0E00 | C7: =IFERROR(VLOOKUP($A:$A,'Matrice Visualizzazione File 1'!$A:$AR,C$1,),"") -> 1U71WEMFRA DIZUN | D7: =IFERROR(VLOOKUP($A:$A,'Matrice Visualizzazione File 1'!$A:$AR,D$1,),"") -> OU | E7: =_xlfn.TEXTJOIN("|",TRUE,Tabella_Traslata[[#This Row],[HN]:[CN]]) -> HN|RN | F7: =_xlfn.TEXTJOIN("|",TRUE,Tabella_Traslata[[#This Row],[Sale office 1]:[Sale office 9]]) -> ABI0|AGIR|ASI0 | G7: =IFERROR(VLOOKUP($A:$A,'Matrice Visualizzazione File 1'!$A:$AR,G$1,),"") -> Yes | H7: =IFERROR(VLOOKUP($A:$A,'Matrice Visualizzazione File 1'!$A:$AR,H$1,),"") -> Cabinet | I7: =IFERROR(VLOOKUP($A:$A,'Matrice Visualizzazione File 1'!$A:$AR,I$1,),"") -> 0 | J7: =IFERROR(VLOOKUP($A:$A,'Matrice Visualizzazione File 1'!$A:$AR,J$1,),"") -> 5 | K7: =IFERROR(VLOOKUP($A:$A,'Matrice Visualizzazione File 1'!$A:$AR,K$1,),"") -> Catologue | L7: =_xlfn.TEXTJOIN("|",TRUE,Tabella_Traslata[[#This Row],[Codice Avviamento 1]:[Codice Avviamento 2]]) | M7: =_xlfn.TEXTJOIN("|",TRUE,Tabella_Traslata[[#This Row],[Accessorio 1]:[Accessorio 5]]) | N7: =IFERROR(VLOOKUP($A:$A,'Matrice Visualizzazione File 1'!$A:$AR,N$1,),"") | O7: =IFERROR(VLOOKUP($A:$A,'Matrice Visualizzazione File 1'!$A:$AR,O$1,),"") | P7: =IFERROR(VLOOKUP($A:$A,'Matrice Visualizzazione File 1'!$A:$AR,P$1,),"") | Q7: =IFERROR(VLOOKUP($A:$A,'Matrice Visualizzazione File 1'!$A:$AR,Q$1,),"") | R7: =IFERROR(VLOOKUP($A:$A,'Matrice Visualizzazione File 1'!$A:$AR,R$1,),"") | S7: =IFERROR(VLOOKUP($A:$A,'Matrice Visualizzazione File 1'!$A:$AR,S$1,),"") -> 0 | T7: =IFERROR(VLOOKUP($A:$A,'Matrice Visualizzazione File 1'!$A:$AR,T$1,),"") | U7: =IFERROR(VLOOKUP($A:$A,'Matrice Visualizzazione File 1'!$A:$AR,U$1,),"") | V7: =IF(IFERROR(VLOOKUP($A:$A,'Matrice Visualizzazione File 1'!$A:$AR,V$1,),"")=0,"",IFERROR(VLOOKUP($A:$A,'Matrice Visualizzazione File 1'!$A:$AR,V$1,),"")) -> HN | W7: =IF(IFERROR(VLOOKUP($A:$A,'Matrice Visualizzazione File 1'!$A:$AR,W$1,),"")=0,"",IFERROR(VLOOKUP($A:$A,'Matrice Visualizzazione File 1'!$A:$AR,W$1,),"")) -> RN | X7: =IF(IFERROR(VLOOKUP($A:$A,'Matrice Visualizzazione File 1'!$A:$AR,X$1,),"")=0,"",IFERROR(VLOOKUP($A:$A,'Matrice Visualizzazione File 1'!$A:$AR,X$1,),"")) | Y7: =IF(IFERROR(VLOOKUP($A:$A,'Matrice Visualizzazione File 1'!$A:$AR,Y$1,),"")=0,"",IFERROR(VLOOKUP($A:$A,'Matrice Visualizzazione File 1'!$A:$AR,Y$1,),"")) -> ABI0 | Z7: =IF(IFERROR(VLOOKUP($A:$A,'Matrice Visualizzazione File 1'!$A:$AR,Z$1,),"")=0,"",IFERROR(VLOOKUP($A:$A,'Matrice Visualizzazione File 1'!$A:$AR,Z$1,),"")) | AA7: =IF(IFERROR(VLOOKUP($A:$A,'Matrice Visualizzazione File 1'!$A:$AR,AA$1,),"")=0,"",IFERROR(VLOOKUP($A:$A,'Matrice Visualizzazione File 1'!$A:$AR,AA$1,),"")) | AB7: =IF(IFERROR(VLOOKUP($A:$A,'Matrice Visualizzazione File 1'!$A:$AR,AB$1,),"")=0,"",IFERROR(VLOOKUP($A:$A,'Matrice Visualizzazione File 1'!$A:$AR,AB$1,),"")) | AC7: =IF(IFERROR(VLOOKUP($A:$A,'Matrice Visualizzazione File 1'!$A:$AR,AC$1,),"")=0,"",IFERROR(VLOOKUP($A:$A,'Matrice Visualizzazione File 1'!$A:$AR,AC$1,),"")) | ... AN7: =IF(IFERROR(VLOOKUP($A:$A,'Matrice Visualizzazione File 1'!$A:$AR,AN$1,),"")=0,"",IFERROR(VLOOKUP($A:$A,'Matrice Visualizzazione File 1'!$A:$AR,AN$1,),""))
A8: =A7+1 -> 3 | B8: =IFERROR(VLOOKUP($A:$A,'Matrice Visualizzazione File 1'!$A:$AR,B$1,),"") -> 0 | C8: =IFERROR(VLOOKUP($A:$A,'Matrice Visualizzazione File 1'!$A:$AR,C$1,),"") -> 0 | D8: =IFERROR(VLOOKUP($A:$A,'Matrice Visualizzazione File 1'!$A:$AR,D$1,),"") -> 0 | E8: =_xlfn.TEXTJOIN("|",TRUE,Tabella_Traslata[[#This Row],[HN]:[CN]]) -> ---|--- | F8: =_xlfn.TEXTJOIN("|",TRUE,Tabella_Traslata[[#This Row],[Sale office 1]:[Sale office 9]]) | G8: =IFERROR(VLOOKUP($A:$A,'Matrice Visualizzazione File 1'!$A:$AR,G$1,),"") -> 0 | H8: =IFERROR(VLOOKUP($A:$A,'Matrice Visualizzazione File 1'!$A:$AR,H$1,),"") -> 0 | I8: =IFERROR(VLOOKUP($A:$A,'Matrice Visualizzazione File 1'!$A:$AR,I$1,),"") -> 0 | J8: =IFERROR(VLOOKUP($A:$A,'Matrice Visualizzazione File 1'!$A:$AR,J$1,),"") -> 0 | K8: =IFERROR(VLOOKUP($A:$A,'Matrice Visualizzazione File 1'!$A:$AR,K$1,),"") -> 0 | L8: =_xlfn.TEXTJOIN("|",TRUE,Tabella_Traslata[[#This Row],[Codice Avviamento 1]:[Codice Avviamento 2]]) | M8: =_xlfn.TEXTJOIN("|",TRUE,Tabella_Traslata[[#This Row],[Accessorio 1]:[Accessorio 5]]) | N8: =IFERROR(VLOOKUP($A:$A,'Matrice Visualizzazione File 1'!$A:$AR,N$1,),"") | O8: =IFERROR(VLOOKUP($A:$A,'Matrice Visualizzazione File 1'!$A:$AR,O$1,),"") | P8: =IFERROR(VLOOKUP($A:$A,'Matrice Visualizzazione File 1'!$A:$AR,P$1,),"") | Q8: =IFERROR(VLOOKUP($A:$A,'Matrice Visualizzazione File 1'!$A:$AR,Q$1,),"") | R8: =IFERROR(VLOOKUP($A:$A,'Matrice Visualizzazione File 1'!$A:$AR,R$1,),"") | S8: =IFERROR(VLOOKUP($A:$A,'Matrice Visualizzazione File 1'!$A:$AR,S$1,),"") -> 0 | T8: =IFERROR(VLOOKUP($A:$A,'Matrice Visualizzazione File 1'!$A:$AR,T$1,),"") | U8: =IFERROR(VLOOKUP($A:$A,'Matrice Visualizzazione File 1'!$A:$AR,U$1,),"") | V8: =IF(IFERROR(VLOOKUP($A:$A,'Matrice Visualizzazione File 1'!$A:$AR,V$1,),"")=0,"",IFERROR(VLOOKUP($A:$A,'Matrice Visualizzazione File 1'!$A:$AR,V$1,),"")) -> --- | W8: =IF(IFERROR(VLOOKUP($A:$A,'Matrice Visualizzazione File 1'!$A:$AR,W$1,),"")=0,"",IFERROR(VLOOKUP($A:$A,'Matrice Visualizzazione File 1'!$A:$AR,W$1,),"")) -> --- | X8: =IF(IFERROR(VLOOKUP($A:$A,'Matrice Visualizzazione File 1'!$A:$AR,X$1,),"")=0,"",IFERROR(VLOOKUP($A:$A,'Matrice Visualizzazione File 1'!$A:$AR,X$1,),"")) | Y8: =IF(IFERROR(VLOOKUP($A:$A,'Matrice Visualizzazione File 1'!$A:$AR,Y$1,),"")=0,"",IFERROR(VLOOKUP($A:$A,'Matrice Visualizzazione File 1'!$A:$AR,Y$1,),"")) | Z8: =IF(IFERROR(VLOOKUP($A:$A,'Matrice Visualizzazione File 1'!$A:$AR,Z$1,),"")=0,"",IFERROR(VLOOKUP($A:$A,'Matrice Visualizzazione File 1'!$A:$AR,Z$1,),"")) | AA8: =IF(IFERROR(VLOOKUP($A:$A,'Matrice Visualizzazione File 1'!$A:$AR,AA$1,),"")=0,"",IFERROR(VLOOKUP($A:$A,'Matrice Visualizzazione File 1'!$A:$AR,AA$1,),"")) | AB8: =IF(IFERROR(VLOOKUP($A:$A,'Matrice Visualizzazione File 1'!$A:$AR,AB$1,),"")=0,"",IFERROR(VLOOKUP($A:$A,'Matrice Visualizzazione File 1'!$A:$AR,AB$1,),"")) | AC8: =IF(IFERROR(VLOOKUP($A:$A,'Matrice Visualizzazione File 1'!$A:$AR,AC$1,),"")=0,"",IFERROR(VLOOKUP($A:$A,'Matrice Visualizzazione File 1'!$A:$AR,AC$1,),"")) | ... AN8: =IF(IFERROR(VLOOKUP($A:$A,'Matrice Visualizzazione File 1'!$A:$AR,AN$1,),"")=0,"",IFERROR(VLOOKUP($A:$A,'Matrice Visualizzazione File 1'!$A:$AR,AN$1,),""))
A9: =A8+1 -> 4 | B9: =IFERROR(VLOOKUP($A:$A,'Matrice Visualizzazione File 1'!$A:$AR,B$1,),"") -> AAC160E00 | C9: =IFERROR(VLOOKUP($A:$A,'Matrice Visualizzazione File 1'!$A:$AR,C$1,),"") | D9: =IFERROR(VLOOKUP($A:$A,'Matrice Visualizzazione File 1'!$A:$AR,D$1,),"") -> IU | E9: =_xlfn.TEXTJOIN("|",TRUE,Tabella_Traslata[[#This Row],[HN]:[CN]]) -> HN|RN | F9: =_xlfn.TEXTJOIN("|",TRUE,Tabella_Traslata[[#This Row],[Sale office 1]:[Sale office 9]]) -> ABI0|AGIR|ASI0 | G9: =IFERROR(VLOOKUP($A:$A,'Matrice Visualizzazione File 1'!$A:$AR,G$1,),"") -> Yes | H9: =IFERROR(VLOOKUP($A:$A,'Matrice Visualizzazione File 1'!$A:$AR,H$1,),"") -> Expert Nordic | I9: =IFERROR(VLOOKUP($A:$A,'Matrice Visualizzazione File 1'!$A:$AR,I$1,),"") -> 0 | J9: =IFERROR(VLOOKUP($A:$A,'Matrice Visualizzazione File 1'!$A:$AR,J$1,),"") -> 5 | K9: =IFERROR(VLOOKUP($A:$A,'Matrice Visualizzazione File 1'!$A:$AR,K$1,),"") -> Catologue | L9: =_xlfn.TEXTJOIN("|",TRUE,Tabella_Traslata[[#This Row],[Codice Avviamento 1]:[Codice Avviamento 2]]) | M9: =_xlfn.TEXTJOIN("|",TRUE,Tabella_Traslata[[#This Row],[Accessorio 1]:[Accessorio 5]]) | N9: =IFERROR(VLOOKUP($A:$A,'Matrice Visualizzazione File 1'!$A:$AR,N$1,),"") | O9: =IFERROR(VLOOKUP($A:$A,'Matrice Visualizzazione File 1'!$A:$AR,O$1,),"") | P9: =IFERROR(VLOOKUP($A:$A,'Matrice Visualizzazione File 1'!$A:$AR,P$1,),"") | Q9: =IFERROR(VLOOKUP($A:$A,'Matrice Visualizzazione File 1'!$A:$AR,Q$1,),"") | R9: =IFERROR(VLOOKUP($A:$A,'Matrice Visualizzazione File 1'!$A:$AR,R$1,),"") | S9: =IFERROR(VLOOKUP($A:$A,'Matrice Visualizzazione File 1'!$A:$AR,S$1,),"") -> 0 | T9: =IFERROR(VLOOKUP($A:$A,'Matrice Visualizzazione File 1'!$A:$AR,T$1,),"") | U9: =IFERROR(VLOOKUP($A:$A,'Matrice Visualizzazione File 1'!$A:$AR,U$1,),"") | V9: =IF(IFERROR(VLOOKUP($A:$A,'Matrice Visualizzazione File 1'!$A:$AR,V$1,),"")=0,"",IFERROR(VLOOKUP($A:$A,'Matrice Visualizzazione File 1'!$A:$AR,V$1,),"")) -> HN | W9: =IF(IFERROR(VLOOKUP($A:$A,'Matrice Visualizzazione File 1'!$A:$AR,W$1,),"")=0,"",IFERROR(VLOOKUP($A:$A,'Matrice Visualizzazione File 1'!$A:$AR,W$1,),"")) -> RN | X9: =IF(IFERROR(VLOOKUP($A:$A,'Matrice Visualizzazione File 1'!$A:$AR,X$1,),"")=0,"",IFERROR(VLOOKUP($A:$A,'Matrice Visualizzazione File 1'!$A:$AR,X$1,),"")) | Y9: =IF(IFERROR(VLOOKUP($A:$A,'Matrice Visualizzazione File 1'!$A:$AR,Y$1,),"")=0,"",IFERROR(VLOOKUP($A:$A,'Matrice Visualizzazione File 1'!$A:$AR,Y$1,),"")) -> ABI0 | Z9: =IF(IFERROR(VLOOKUP($A:$A,'Matrice Visualizzazione File 1'!$A:$AR,Z$1,),"")=0,"",IFERROR(VLOOKUP($A:$A,'Matrice Visualizzazione File 1'!$A:$AR,Z$1,),"")) | AA9: =IF(IFERROR(VLOOKUP($A:$A,'Matrice Visualizzazione File 1'!$A:$AR,AA$1,),"")=0,"",IFERROR(VLOOKUP($A:$A,'Matrice Visualizzazione File 1'!$A:$AR,AA$1,),"")) | AB9: =IF(IFERROR(VLOOKUP($A:$A,'Matrice Visualizzazione File 1'!$A:$AR,AB$1,),"")=0,"",IFERROR(VLOOKUP($A:$A,'Matrice Visualizzazione File 1'!$A:$AR,AB$1,),"")) | AC9: =IF(IFERROR(VLOOKUP($A:$A,'Matrice Visualizzazione File 1'!$A:$AR,AC$1,),"")=0,"",IFERROR(VLOOKUP($A:$A,'Matrice Visualizzazione File 1'!$A:$AR,AC$1,),"")) | ... AN9: =IF(IFERROR(VLOOKUP($A:$A,'Matrice Visualizzazione File 1'!$A:$AR,AN$1,),"")=0,"",IFERROR(VLOOKUP($A:$A,'Matrice Visualizzazione File 1'!$A:$AR,AN$1,),""))
A10: =A9+1 -> 5 | B10: =IFERROR(VLOOKUP($A:$A,'Matrice Visualizzazione File 1'!$A:$AR,B$1,),"") -> AAC180E00 | C10: =IFERROR(VLOOKUP($A:$A,'Matrice Visualizzazione File 1'!$A:$AR,C$1,),"") -> 1U25KEHFRA-NR | D10: =IFERROR(VLOOKUP($A:$A,'Matrice Visualizzazione File 1'!$A:$AR,D$1,),"") -> OU | E10: =_xlfn.TEXTJOIN("|",TRUE,Tabella_Traslata[[#This Row],[HN]:[CN]]) -> HN|RN | F10: =_xlfn.TEXTJOIN("|",TRUE,Tabella_Traslata[[#This Row],[Sale office 1]:[Sale office 9]]) -> ABI0|AGIR|ASI0 | G10: =IFERROR(VLOOKUP($A:$A,'Matrice Visualizzazione File 1'!$A:$AR,G$1,),"") -> Yes | H10: =IFERROR(VLOOKUP($A:$A,'Matrice Visualizzazione File 1'!$A:$AR,H$1,),"") -> Expert Nordic | I10: =IFERROR(VLOOKUP($A:$A,'Matrice Visualizzazione File 1'!$A:$AR,I$1,),"") -> 0 | J10: =IFERROR(VLOOKUP($A:$A,'Matrice Visualizzazione File 1'!$A:$AR,J$1,),"") -> 5 | K10: =IFERROR(VLOOKUP($A:$A,'Matrice Visualizzazione File 1'!$A:$AR,K$1,),"") -> Catologue | L10: =_xlfn.TEXTJOIN("|",TRUE,Tabella_Traslata[[#This Row],[Codice Avviamento 1]:[Codice Avviamento 2]]) | M10: =_xlfn.TEXTJOIN("|",TRUE,Tabella_Traslata[[#This Row],[Accessorio 1]:[Accessorio 5]]) | N10: =IFERROR(VLOOKUP($A:$A,'Matrice Visualizzazione File 1'!$A:$AR,N$1,),"") | O10: =IFERROR(VLOOKUP($A:$A,'Matrice Visualizzazione File 1'!$A:$AR,O$1,),"") | P10: =IFERROR(VLOOKUP($A:$A,'Matrice Visualizzazione File 1'!$A:$AR,P$1,),"") | Q10: =IFERROR(VLOOKUP($A:$A,'Matrice Visualizzazione File 1'!$A:$AR,Q$1,),"") | R10: =IFERROR(VLOOKUP($A:$A,'Matrice Visualizzazione File 1'!$A:$AR,R$1,),"") | S10: =IFERROR(VLOOKUP($A:$A,'Matrice Visualizzazione File 1'!$A:$AR,S$1,),"") -> 0 | T10: =IFERROR(VLOOKUP($A:$A,'Matrice Visualizzazione File 1'!$A:$AR,T$1,),"") | U10: =IFERROR(VLOOKUP($A:$A,'Matrice Visualizzazione File 1'!$A:$AR,U$1,),"") | V10: =IF(IFERROR(VLOOKUP($A:$A,'Matrice Visualizzazione File 1'!$A:$AR,V$1,),"")=0,"",IFERROR(VLOOKUP($A:$A,'Matrice Visualizzazione File 1'!$A:$AR,V$1,),"")) -> HN | W10: =IF(IFERROR(VLOOKUP($A:$A,'Matrice Visualizzazione File 1'!$A:$AR,W$1,),"")=0,"",IFERROR(VLOOKUP($A:$A,'Matrice Visualizzazione File 1'!$A:$AR,W$1,),"")) -> RN | X10: =IF(IFERROR(VLOOKUP($A:$A,'Matrice Visualizzazione File 1'!$A:$AR,X$1,),"")=0,"",IFERROR(VLOOKUP($A:$A,'Matrice Visualizzazione File 1'!$A:$AR,X$1,),"")) | Y10: =IF(IFERROR(VLOOKUP($A:$A,'Matrice Visualizzazione File 1'!$A:$AR,Y$1,),"")=0,"",IFERROR(VLOOKUP($A:$A,'Matrice Visualizzazione File 1'!$A:$AR,Y$1,),"")) -> ABI0 | Z10: =IF(IFERROR(VLOOKUP($A:$A,'Matrice Visualizzazione File 1'!$A:$AR,Z$1,),"")=0,"",IFERROR(VLOOKUP($A:$A,'Matrice Visualizzazione File 1'!$A:$AR,Z$1,),"")) | AA10: =IF(IFERROR(VLOOKUP($A:$A,'Matrice Visualizzazione File 1'!$A:$AR,AA$1,),"")=0,"",IFERROR(VLOOKUP($A:$A,'Matrice Visualizzazione File 1'!$A:$AR,AA$1,),"")) | AB10: =IF(IFERROR(VLOOKUP($A:$A,'Matrice Visualizzazione File 1'!$A:$AR,AB$1,),"")=0,"",IFERROR(VLOOKUP($A:$A,'Matrice Visualizzazione File 1'!$A:$AR,AB$1,),"")) | AC10: =IF(IFERROR(VLOOKUP($A:$A,'Matrice Visualizzazione File 1'!$A:$AR,AC$1,),"")=0,"",IFERROR(VLOOKUP($A:$A,'Matrice Visualizzazione File 1'!$A:$AR,AC$1,),"")) | ... AN10: =IF(IFERROR(VLOOKUP($A:$A,'Matrice Visualizzazione File 1'!$A:$AR,AN$1,),"")=0,"",IFERROR(VLOOKUP($A:$A,'Matrice Visualizzazione File 1'!$A:$AR,AN$1,),""))
A11: =A10+1 -> 6 | B11: =IFERROR(VLOOKUP($A:$A,'Matrice Visualizzazione File 1'!$A:$AR,B$1,),"") -> AAC170E00 | C11: =IFERROR(VLOOKUP($A:$A,'Matrice Visualizzazione File 1'!$A:$AR,C$1,),"") -> AS35XCHHRA-NR | D11: =IFERROR(VLOOKUP($A:$A,'Matrice Visualizzazione File 1'!$A:$AR,D$1,),"") -> IU | E11: =_xlfn.TEXTJOIN("|",TRUE,Tabella_Traslata[[#This Row],[HN]:[CN]]) -> HN|RN | F11: =_xlfn.TEXTJOIN("|",TRUE,Tabella_Traslata[[#This Row],[Sale office 1]:[Sale office 9]]) -> ABI0|AGIR|ASI0 | G11: =IFERROR(VLOOKUP($A:$A,'Matrice Visualizzazione File 1'!$A:$AR,G$1,),"") -> Yes | H11: =IFERROR(VLOOKUP($A:$A,'Matrice Visualizzazione File 1'!$A:$AR,H$1,),"") -> Expert Nordic | I11: =IFERROR(VLOOKUP($A:$A,'Matrice Visualizzazione File 1'!$A:$AR,I$1,),"") -> 0 | J11: =IFERROR(VLOOKUP($A:$A,'Matrice Visualizzazione File 1'!$A:$AR,J$1,),"") -> 5 | K11: =IFERROR(VLOOKUP($A:$A,'Matrice Visualizzazione File 1'!$A:$AR,K$1,),"") -> Catologue | L11: =_xlfn.TEXTJOIN("|",TRUE,Tabella_Traslata[[#This Row],[Codice Avviamento 1]:[Codice Avviamento 2]]) | M11: =_xlfn.TEXTJOIN("|",TRUE,Tabella_Traslata[[#This Row],[Accessorio 1]:[Accessorio 5]]) | N11: =IFERROR(VLOOKUP($A:$A,'Matrice Visualizzazione File 1'!$A:$AR,N$1,),"") | O11: =IFERROR(VLOOKUP($A:$A,'Matrice Visualizzazione File 1'!$A:$AR,O$1,),"") | P11: =IFERROR(VLOOKUP($A:$A,'Matrice Visualizzazione File 1'!$A:$AR,P$1,),"") | Q11: =IFERROR(VLOOKUP($A:$A,'Matrice Visualizzazione File 1'!$A:$AR,Q$1,),"") | R11: =IFERROR(VLOOKUP($A:$A,'Matrice Visualizzazione File 1'!$A:$AR,R$1,),"") | S11: =IFERROR(VLOOKUP($A:$A,'Matrice Visualizzazione File 1'!$A:$AR,S$1,),"") -> 0 | T11: =IFERROR(VLOOKUP($A:$A,'Matrice Visualizzazione File 1'!$A:$AR,T$1,),"") | U11: =IFERROR(VLOOKUP($A:$A,'Matrice Visualizzazione File 1'!$A:$AR,U$1,),"") | V11: =IF(IFERROR(VLOOKUP($A:$A,'Matrice Visualizzazione File 1'!$A:$AR,V$1,),"")=0,"",IFERROR(VLOOKUP($A:$A,'Matrice Visualizzazione File 1'!$A:$AR,V$1,),"")) -> HN | W11: =IF(IFERROR(VLOOKUP($A:$A,'Matrice Visualizzazione File 1'!$A:$AR,W$1,),"")=0,"",IFERROR(VLOOKUP($A:$A,'Matrice Visualizzazione File 1'!$A:$AR,W$1,),"")) -> RN | X11: =IF(IFERROR(VLOOKUP($A:$A,'Matrice Visualizzazione File 1'!$A:$AR,X$1,),"")=0,"",IFERROR(VLOOKUP($A:$A,'Matrice Visualizzazione File 1'!$A:$AR,X$1,),"")) | Y11: =IF(IFERROR(VLOOKUP($A:$A,'Matrice Visualizzazione File 1'!$A:$AR,Y$1,),"")=0,"",IFERROR(VLOOKUP($A:$A,'Matrice Visualizzazione File 1'!$A:$AR,Y$1,),"")) -> ABI0 | Z11: =IF(IFERROR(VLOOKUP($A:$A,'Matrice Visualizzazione File 1'!$A:$AR,Z$1,),"")=0,"",IFERROR(VLOOKUP($A:$A,'Matrice Visualizzazione File 1'!$A:$AR,Z$1,),"")) | AA11: =IF(IFERROR(VLOOKUP($A:$A,'Matrice Visualizzazione File 1'!$A:$AR,AA$1,),"")=0,"",IFERROR(VLOOKUP($A:$A,'Matrice Visualizzazione File 1'!$A:$AR,AA$1,),"")) | AB11: =IF(IFERROR(VLOOKUP($A:$A,'Matrice Visualizzazione File 1'!$A:$AR,AB$1,),"")=0,"",IFERROR(VLOOKUP($A:$A,'Matrice Visualizzazione File 1'!$A:$AR,AB$1,),"")) | AC11: =IF(IFERROR(VLOOKUP($A:$A,'Matrice Visualizzazione File 1'!$A:$AR,AC$1,),"")=0,"",IFERROR(VLOOKUP($A:$A,'Matrice Visualizzazione File 1'!$A:$AR,AC$1,),"")) | ... AN11: =IF(IFERROR(VLOOKUP($A:$A,'Matrice Visualizzazione File 1'!$A:$AR,AN$1,),"")=0,"",IFERROR(VLOOKUP($A:$A,'Matrice Visualizzazione File 1'!$A:$AR,AN$1,),""))
A12: =A11+1 -> 7 | B12: =IFERROR(VLOOKUP($A:$A,'Matrice Visualizzazione File 1'!$A:$AR,B$1,),"") -> AAC190E00 | C12: =IFERROR(VLOOKUP($A:$A,'Matrice Visualizzazione File 1'!$A:$AR,C$1,),"") -> 1U35KEHFRA-NR | D12: =IFERROR(VLOOKUP($A:$A,'Matrice Visualizzazione File 1'!$A:$AR,D$1,),"") -> OU | E12: =_xlfn.TEXTJOIN("|",TRUE,Tabella_Traslata[[#This Row],[HN]:[CN]]) -> HN|RN | F12: =_xlfn.TEXTJOIN("|",TRUE,Tabella_Traslata[[#This Row],[Sale office 1]:[Sale office 9]]) -> ABI0|AGIR|ASI0 | G12: =IFERROR(VLOOKUP($A:$A,'Matrice Visualizzazione File 1'!$A:$AR,G$1,),"") -> Yes | H12: =IFERROR(VLOOKUP($A:$A,'Matrice Visualizzazione File 1'!$A:$AR,H$1,),"") -> Expert Nordic | I12: =IFERROR(VLOOKUP($A:$A,'Matrice Visualizzazione File 1'!$A:$AR,I$1,),"") -> 0 | J12: =IFERROR(VLOOKUP($A:$A,'Matrice Visualizzazione File 1'!$A:$AR,J$1,),"") -> 5 | K12: =IFERROR(VLOOKUP($A:$A,'Matrice Visualizzazione File 1'!$A:$AR,K$1,),"") -> Catologue | L12: =_xlfn.TEXTJOIN("|",TRUE,Tabella_Traslata[[#This Row],[Codice Avviamento 1]:[Codice Avviamento 2]]) | M12: =_xlfn.TEXTJOIN("|",TRUE,Tabella_Traslata[[#This Row],[Accessorio 1]:[Accessorio 5]]) | N12: =IFERROR(VLOOKUP($A:$A,'Matrice Visualizzazione File 1'!$A:$AR,N$1,),"") | O12: =IFERROR(VLOOKUP($A:$A,'Matrice Visualizzazione File 1'!$A:$AR,O$1,),"") | P12: =IFERROR(VLOOKUP($A:$A,'Matrice Visualizzazione File 1'!$A:$AR,P$1,),"") | Q12: =IFERROR(VLOOKUP($A:$A,'Matrice Visualizzazione File 1'!$A:$AR,Q$1,),"") | R12: =IFERROR(VLOOKUP($A:$A,'Matrice Visualizzazione File 1'!$A:$AR,R$1,),"") | S12: =IFERROR(VLOOKUP($A:$A,'Matrice Visualizzazione File 1'!$A:$AR,S$1,),"") -> 0 | T12: =IFERROR(VLOOKUP($A:$A,'Matrice Visualizzazione File 1'!$A:$AR,T$1,),"") | U12: =IFERROR(VLOOKUP($A:$A,'Matrice Visualizzazione File 1'!$A:$AR,U$1,),"") | V12: =IF(IFERROR(VLOOKUP($A:$A,'Matrice Visualizzazione File 1'!$A:$AR,V$1,),"")=0,"",IFERROR(VLOOKUP($A:$A,'Matrice Visualizzazione File 1'!$A:$AR,V$1,),"")) -> HN | W12: =IF(IFERROR(VLOOKUP($A:$A,'Matrice Visualizzazione File 1'!$A:$AR,W$1,),"")=0,"",IFERROR(VLOOKUP($A:$A,'Matrice Visualizzazione File 1'!$A:$AR,W$1,),"")) -> RN | X12: =IF(IFERROR(VLOOKUP($A:$A,'Matrice Visualizzazione File 1'!$A:$AR,X$1,),"")=0,"",IFERROR(VLOOKUP($A:$A,'Matrice Visualizzazione File 1'!$A:$AR,X$1,),"")) | Y12: =IF(IFERROR(VLOOKUP($A:$A,'Matrice Visualizzazione File 1'!$A:$AR,Y$1,),"")=0,"",IFERROR(VLOOKUP($A:$A,'Matrice Visualizzazione File 1'!$A:$AR,Y$1,),"")) -> ABI0 | Z12: =IF(IFERROR(VLOOKUP($A:$A,'Matrice Visualizzazione File 1'!$A:$AR,Z$1,),"")=0,"",IFERROR(VLOOKUP($A:$A,'Matrice Visualizzazione File 1'!$A:$AR,Z$1,),"")) | AA12: =IF(IFERROR(VLOOKUP($A:$A,'Matrice Visualizzazione File 1'!$A:$AR,AA$1,),"")=0,"",IFERROR(VLOOKUP($A:$A,'Matrice Visualizzazione File 1'!$A:$AR,AA$1,),"")) | AB12: =IF(IFERROR(VLOOKUP($A:$A,'Matrice Visualizzazione File 1'!$A:$AR,AB$1,),"")=0,"",IFERROR(VLOOKUP($A:$A,'Matrice Visualizzazione File 1'!$A:$AR,AB$1,),"")) | AC12: =IF(IFERROR(VLOOKUP($A:$A,'Matrice Visualizzazione File 1'!$A:$AR,AC$1,),"")=0,"",IFERROR(VLOOKUP($A:$A,'Matrice Visualizzazione File 1'!$A:$AR,AC$1,),"")) | ... AN12: =IF(IFERROR(VLOOKUP($A:$A,'Matrice Visualizzazione File 1'!$A:$AR,AN$1,),"")=0,"",IFERROR(VLOOKUP($A:$A,'Matrice Visualizzazione File 1'!$A:$AR,AN$1,),""))
A13: =A12+1 -> 8 | B13: =IFERROR(VLOOKUP($A:$A,'Matrice Visualizzazione File 1'!$A:$AR,B$1,),"") -> AABQN6E00 | C13: =IFERROR(VLOOKUP($A:$A,'Matrice Visualizzazione File 1'!$A:$AR,C$1,),"") -> 1U35MEHFRA-1 | D13: =IFERROR(VLOOKUP($A:$A,'Matrice Visualizzazione File 1'!$A:$AR,D$1,),"") -> OU | E13: =_xlfn.TEXTJOIN("|",TRUE,Tabella_Traslata[[#This Row],[HN]:[CN]]) -> RN | F13: =_xlfn.TEXTJOIN("|",TRUE,Tabella_Traslata[[#This Row],[Sale office 1]:[Sale office 9]]) -> AGIR|ASI0 | G13: =IFERROR(VLOOKUP($A:$A,'Matrice Visualizzazione File 1'!$A:$AR,G$1,),"") -> Yes | H13: =IFERROR(VLOOKUP($A:$A,'Matrice Visualizzazione File 1'!$A:$AR,H$1,),"") -> Flexis Nordic | I13: =IFERROR(VLOOKUP($A:$A,'Matrice Visualizzazione File 1'!$A:$AR,I$1,),"") -> 0 | J13: =IFERROR(VLOOKUP($A:$A,'Matrice Visualizzazione File 1'!$A:$AR,J$1,),"") -> 5 | K13: =IFERROR(VLOOKUP($A:$A,'Matrice Visualizzazione File 1'!$A:$AR,K$1,),"") -> Catologue | L13: =_xlfn.TEXTJOIN("|",TRUE,Tabella_Traslata[[#This Row],[Codice Avviamento 1]:[Codice Avviamento 2]]) | M13: =_xlfn.TEXTJOIN("|",TRUE,Tabella_Traslata[[#This Row],[Accessorio 1]:[Accessorio 5]]) | N13: =IFERROR(VLOOKUP($A:$A,'Matrice Visualizzazione File 1'!$A:$AR,N$1,),"") | O13: =IFERROR(VLOOKUP($A:$A,'Matrice Visualizzazione File 1'!$A:$AR,O$1,),"") | P13: =IFERROR(VLOOKUP($A:$A,'Matrice Visualizzazione File 1'!$A:$AR,P$1,),"") | Q13: =IFERROR(VLOOKUP($A:$A,'Matrice Visualizzazione File 1'!$A:$AR,Q$1,),"") | R13: =IFERROR(VLOOKUP($A:$A,'Matrice Visualizzazione File 1'!$A:$AR,R$1,),"") | S13: =IFERROR(VLOOKUP($A:$A,'Matrice Visualizzazione File 1'!$A:$AR,S$1,),"") -> 0 | T13: =IFERROR(VLOOKUP($A:$A,'Matrice Visualizzazione File 1'!$A:$AR,T$1,),"") | U13: =IFERROR(VLOOKUP($A:$A,'Matrice Visualizzazione File 1'!$A:$AR,U$1,),"") | V13: =IF(IFERROR(VLOOKUP($A:$A,'Matrice Visualizzazione File 1'!$A:$AR,V$1,),"")=0,"",IFERROR(VLOOKUP($A:$A,'Matrice Visualizzazione File 1'!$A:$AR,V$1,),"")) | W13: =IF(IFERROR(VLOOKUP($A:$A,'Matrice Visualizzazione File 1'!$A:$AR,W$1,),"")=0,"",IFERROR(VLOOKUP($A:$A,'Matrice Visualizzazione File 1'!$A:$AR,W$1,),"")) -> RN | X13: =IF(IFERROR(VLOOKUP($A:$A,'Matrice Visualizzazione File 1'!$A:$AR,X$1,),"")=0,"",IFERROR(VLOOKUP($A:$A,'Matrice Visualizzazione File 1'!$A:$AR,X$1,),"")) | Y13: =IF(IFERROR(VLOOKUP($A:$A,'Matrice Visualizzazione File 1'!$A:$AR,Y$1,),"")=0,"",IFERROR(VLOOKUP($A:$A,'Matrice Visualizzazione File 1'!$A:$AR,Y$1,),"")) | Z13: =IF(IFERROR(VLOOKUP($A:$A,'Matrice Visualizzazione File 1'!$A:$AR,Z$1,),"")=0,"",IFERROR(VLOOKUP($A:$A,'Matrice Visualizzazione File 1'!$A:$AR,Z$1,),"")) | AA13: =IF(IFERROR(VLOOKUP($A:$A,'Matrice Visualizzazione File 1'!$A:$AR,AA$1,),"")=0,"",IFERROR(VLOOKUP($A:$A,'Matrice Visualizzazione File 1'!$A:$AR,AA$1,),"")) | AB13: =IF(IFERROR(VLOOKUP($A:$A,'Matrice Visualizzazione File 1'!$A:$AR,AB$1,),"")=0,"",IFERROR(VLOOKUP($A:$A,'Matrice Visualizzazione File 1'!$A:$AR,AB$1,),"")) | AC13: =IF(IFERROR(VLOOKUP($A:$A,'Matrice Visualizzazione File 1'!$A:$AR,AC$1,),"")=0,"",IFERROR(VLOOKUP($A:$A,'Matrice Visualizzazione File 1'!$A:$AR,AC$1,),"")) | ... AN13: =IF(IFERROR(VLOOKUP($A:$A,'Matrice Visualizzazione File 1'!$A:$AR,AN$1,),"")=0,"",IFERROR(VLOOKUP($A:$A,'Matrice Visualizzazione File 1'!$A:$AR,AN$1,),""))
A14: =A13+1 -> 9 | B14: =IFERROR(VLOOKUP($A:$A,'Matrice Visualizzazione File 1'!$A:$AR,B$1,),"") -> AAC152E00 | C14: =IFERROR(VLOOKUP($A:$A,'Matrice Visualizzazione File 1'!$A:$AR,C$1,),"") -> 1U50KEFFRA-1 | D14: =IFERROR(VLOOKUP($A:$A,'Matrice Visualizzazione File 1'!$A:$AR,D$1,),"") -> OU | E14: =_xlfn.TEXTJOIN("|",TRUE,Tabella_Traslata[[#This Row],[HN]:[CN]]) -> RN | F14: =_xlfn.TEXTJOIN("|",TRUE,Tabella_Traslata[[#This Row],[Sale office 1]:[Sale office 9]]) -> AGIR|ASI0 | G14: =IFERROR(VLOOKUP($A:$A,'Matrice Visualizzazione File 1'!$A:$AR,G$1,),"") -> Yes | H14: =IFERROR(VLOOKUP($A:$A,'Matrice Visualizzazione File 1'!$A:$AR,H$1,),"") -> Flexis Nordic | I14: =IFERROR(VLOOKUP($A:$A,'Matrice Visualizzazione File 1'!$A:$AR,I$1,),"") -> 0 | J14: =IFERROR(VLOOKUP($A:$A,'Matrice Visualizzazione File 1'!$A:$AR,J$1,),"") -> 5 | K14: =IFERROR(VLOOKUP($A:$A,'Matrice Visualizzazione File 1'!$A:$AR,K$1,),"") -> Catologue | L14: =_xlfn.TEXTJOIN("|",TRUE,Tabella_Traslata[[#This Row],[Codice Avviamento 1]:[Codice Avviamento 2]]) | M14: =_xlfn.TEXTJOIN("|",TRUE,Tabella_Traslata[[#This Row],[Accessorio 1]:[Accessorio 5]]) | N14: =IFERROR(VLOOKUP($A:$A,'Matrice Visualizzazione File 1'!$A:$AR,N$1,),"") | O14: =IFERROR(VLOOKUP($A:$A,'Matrice Visualizzazione File 1'!$A:$AR,O$1,),"") | P14: =IFERROR(VLOOKUP($A:$A,'Matrice Visualizzazione File 1'!$A:$AR,P$1,),"") | Q14: =IFERROR(VLOOKUP($A:$A,'Matrice Visualizzazione File 1'!$A:$AR,Q$1,),"") | R14: =IFERROR(VLOOKUP($A:$A,'Matrice Visualizzazione File 1'!$A:$AR,R$1,),"") | S14: =IFERROR(VLOOKUP($A:$A,'Matrice Visualizzazione File 1'!$A:$AR,S$1,),"") -> 0 | T14: =IFERROR(VLOOKUP($A:$A,'Matrice Visualizzazione File 1'!$A:$AR,T$1,),"") | U14: =IFERROR(VLOOKUP($A:$A,'Matrice Visualizzazione File 1'!$A:$AR,U$1,),"") | V14: =IF(IFERROR(VLOOKUP($A:$A,'Matrice Visualizzazione File 1'!$A:$AR,V$1,),"")=0,"",IFERROR(VLOOKUP($A:$A,'Matrice Visualizzazione File 1'!$A:$AR,V$1,),"")) | W14: =IF(IFERROR(VLOOKUP($A:$A,'Matrice Visualizzazione File 1'!$A:$AR,W$1,),"")=0,"",IFERROR(VLOOKUP($A:$A,'Matrice Visualizzazione File 1'!$A:$AR,W$1,),"")) -> RN | X14: =IF(IFERROR(VLOOKUP($A:$A,'Matrice Visualizzazione File 1'!$A:$AR,X$1,),"")=0,"",IFERROR(VLOOKUP($A:$A,'Matrice Visualizzazione File 1'!$A:$AR,X$1,),"")) | Y14: =IF(IFERROR(VLOOKUP($A:$A,'Matrice Visualizzazione File 1'!$A:$AR,Y$1,),"")=0,"",IFERROR(VLOOKUP($A:$A,'Matrice Visualizzazione File 1'!$A:$AR,Y$1,),"")) | Z14: =IF(IFERROR(VLOOKUP($A:$A,'Matrice Visualizzazione File 1'!$A:$AR,Z$1,),"")=0,"",IFERROR(VLOOKUP($A:$A,'Matrice Visualizzazione File 1'!$A:$AR,Z$1,),"")) | AA14: =IF(IFERROR(VLOOKUP($A:$A,'Matrice Visualizzazione File 1'!$A:$AR,AA$1,),"")=0,"",IFERROR(VLOOKUP($A:$A,'Matrice Visualizzazione File 1'!$A:$AR,AA$1,),"")) | AB14: =IF(IFERROR(VLOOKUP($A:$A,'Matrice Visualizzazione File 1'!$A:$AR,AB$1,),"")=0,"",IFERROR(VLOOKUP($A:$A,'Matrice Visualizzazione File 1'!$A:$AR,AB$1,),"")) | AC14: =IF(IFERROR(VLOOKUP($A:$A,'Matrice Visualizzazione File 1'!$A:$AR,AC$1,),"")=0,"",IFERROR(VLOOKUP($A:$A,'Matrice Visualizzazione File 1'!$A:$AR,AC$1,),"")) | ... AN14: =IF(IFERROR(VLOOKUP($A:$A,'Matrice Visualizzazione File 1'!$A:$AR,AN$1,),"")=0,"",IFERROR(VLOOKUP($A:$A,'Matrice Visualizzazione File 1'!$A:$AR,AN$1,),""))
A15: =A14+1 -> 10 | B15: =IFERROR(VLOOKUP($A:$A,'Matrice Visualizzazione File 1'!$A:$AR,B$1,),"") -> 0 | C15: =IFERROR(VLOOKUP($A:$A,'Matrice Visualizzazione File 1'!$A:$AR,C$1,),"") -> 0 | D15: =IFERROR(VLOOKUP($A:$A,'Matrice Visualizzazione File 1'!$A:$AR,D$1,),"") -> 0 | E15: =_xlfn.TEXTJOIN("|",TRUE,Tabella_Traslata[[#This Row],[HN]:[CN]]) -> ---|--- | F15: =_xlfn.TEXTJOIN("|",TRUE,Tabella_Traslata[[#This Row],[Sale office 1]:[Sale office 9]]) | G15: =IFERROR(VLOOKUP($A:$A,'Matrice Visualizzazione File 1'!$A:$AR,G$1,),"") -> 0 | H15: =IFERROR(VLOOKUP($A:$A,'Matrice Visualizzazione File 1'!$A:$AR,H$1,),"") -> 0 | I15: =IFERROR(VLOOKUP($A:$A,'Matrice Visualizzazione File 1'!$A:$AR,I$1,),"") -> 0 | J15: =IFERROR(VLOOKUP($A:$A,'Matrice Visualizzazione File 1'!$A:$AR,J$1,),"") -> 0 | K15: =IFERROR(VLOOKUP($A:$A,'Matrice Visualizzazione File 1'!$A:$AR,K$1,),"") -> 0 | L15: =_xlfn.TEXTJOIN("|",TRUE,Tabella_Traslata[[#This Row],[Codice Avviamento 1]:[Codice Avviamento 2]]) | M15: =_xlfn.TEXTJOIN("|",TRUE,Tabella_Traslata[[#This Row],[Accessorio 1]:[Accessorio 5]]) | N15: =IFERROR(VLOOKUP($A:$A,'Matrice Visualizzazione File 1'!$A:$AR,N$1,),"") | O15: =IFERROR(VLOOKUP($A:$A,'Matrice Visualizzazione File 1'!$A:$AR,O$1,),"") | P15: =IFERROR(VLOOKUP($A:$A,'Matrice Visualizzazione File 1'!$A:$AR,P$1,),"") | Q15: =IFERROR(VLOOKUP($A:$A,'Matrice Visualizzazione File 1'!$A:$AR,Q$1,),"") | R15: =IFERROR(VLOOKUP($A:$A,'Matrice Visualizzazione File 1'!$A:$AR,R$1,),"") | S15: =IFERROR(VLOOKUP($A:$A,'Matrice Visualizzazione File 1'!$A:$AR,S$1,),"") -> 0 | T15: =IFERROR(VLOOKUP($A:$A,'Matrice Visualizzazione File 1'!$A:$AR,T$1,),"") | U15: =IFERROR(VLOOKUP($A:$A,'Matrice Visualizzazione File 1'!$A:$AR,U$1,),"") | V15: =IF(IFERROR(VLOOKUP($A:$A,'Matrice Visualizzazione File 1'!$A:$AR,V$1,),"")=0,"",IFERROR(VLOOKUP($A:$A,'Matrice Visualizzazione File 1'!$A:$AR,V$1,),"")) -> --- | W15: =IF(IFERROR(VLOOKUP($A:$A,'Matrice Visualizzazione File 1'!$A:$AR,W$1,),"")=0,"",IFERROR(VLOOKUP($A:$A,'Matrice Visualizzazione File 1'!$A:$AR,W$1,),"")) -> --- | X15: =IF(IFERROR(VLOOKUP($A:$A,'Matrice Visualizzazione File 1'!$A:$AR,X$1,),"")=0,"",IFERROR(VLOOKUP($A:$A,'Matrice Visualizzazione File 1'!$A:$AR,X$1,),"")) | Y15: =IF(IFERROR(VLOOKUP($A:$A,'Matrice Visualizzazione File 1'!$A:$AR,Y$1,),"")=0,"",IFERROR(VLOOKUP($A:$A,'Matrice Visualizzazione File 1'!$A:$AR,Y$1,),"")) | Z15: =IF(IFERROR(VLOOKUP($A:$A,'Matrice Visualizzazione File 1'!$A:$AR,Z$1,),"")=0,"",IFERROR(VLOOKUP($A:$A,'Matrice Visualizzazione File 1'!$A:$AR,Z$1,),"")) | AA15: =IF(IFERROR(VLOOKUP($A:$A,'Matrice Visualizzazione File 1'!$A:$AR,AA$1,),"")=0,"",IFERROR(VLOOKUP($A:$A,'Matrice Visualizzazione File 1'!$A:$AR,AA$1,),"")) | AB15: =IF(IFERROR(VLOOKUP($A:$A,'Matrice Visualizzazione File 1'!$A:$AR,AB$1,),"")=0,"",IFERROR(VLOOKUP($A:$A,'Matrice Visualizzazione File 1'!$A:$AR,AB$1,),"")) | AC15: =IF(IFERROR(VLOOKUP($A:$A,'Matrice Visualizzazione File 1'!$A:$AR,AC$1,),"")=0,"",IFERROR(VLOOKUP($A:$A,'Matrice Visualizzazione File 1'!$A:$AR,AC$1,),"")) | ... AN15: =IF(IFERROR(VLOOKUP($A:$A,'Matrice Visualizzazione File 1'!$A:$AR,AN$1,),"")=0,"",IFERROR(VLOOKUP($A:$A,'Matrice Visualizzazione File 1'!$A:$AR,AN$1,),""))
A16: =A15+1 -> 11 | B16: =IFERROR(VLOOKUP($A:$A,'Matrice Visualizzazione File 1'!$A:$AR,B$1,),"") -> AACCP0E00 | C16: =IFERROR(VLOOKUP($A:$A,'Matrice Visualizzazione File 1'!$A:$AR,C$1,),"") -> AS25PCHHRA-NR | D16: =IFERROR(VLOOKUP($A:$A,'Matrice Visualizzazione File 1'!$A:$AR,D$1,),"") -> IU | E16: =_xlfn.TEXTJOIN("|",TRUE,Tabella_Traslata[[#This Row],[HN]:[CN]]) -> RN | F16: =_xlfn.TEXTJOIN("|",TRUE,Tabella_Traslata[[#This Row],[Sale office 1]:[Sale office 9]]) -> AGIR|ASI0 | G16: =IFERROR(VLOOKUP($A:$A,'Matrice Visualizzazione File 1'!$A:$AR,G$1,),"") -> Yes | H16: =IFERROR(VLOOKUP($A:$A,'Matrice Visualizzazione File 1'!$A:$AR,H$1,),"") -> Pearl Nordic | I16: =IFERROR(VLOOKUP($A:$A,'Matrice Visualizzazione File 1'!$A:$AR,I$1,),"") -> 0 | J16: =IFERROR(VLOOKUP($A:$A,'Matrice Visualizzazione File 1'!$A:$AR,J$1,),"") -> 5 | K16: =IFERROR(VLOOKUP($A:$A,'Matrice Visualizzazione File 1'!$A:$AR,K$1,),"") -> Catologue | L16: =_xlfn.TEXTJOIN("|",TRUE,Tabella_Traslata[[#This Row],[Codice Avviamento 1]:[Codice Avviamento 2]]) | M16: =_xlfn.TEXTJOIN("|",TRUE,Tabella_Traslata[[#This Row],[Accessorio 1]:[Accessorio 5]]) | N16: =IFERROR(VLOOKUP($A:$A,'Matrice Visualizzazione File 1'!$A:$AR,N$1,),"") | O16: =IFERROR(VLOOKUP($A:$A,'Matrice Visualizzazione File 1'!$A:$AR,O$1,),"") | P16: =IFERROR(VLOOKUP($A:$A,'Matrice Visualizzazione File 1'!$A:$AR,P$1,),"") | Q16: =IFERROR(VLOOKUP($A:$A,'Matrice Visualizzazione File 1'!$A:$AR,Q$1,),"") | R16: =IFERROR(VLOOKUP($A:$A,'Matrice Visualizzazione File 1'!$A:$AR,R$1,),"") | S16: =IFERROR(VLOOKUP($A:$A,'Matrice Visualizzazione File 1'!$A:$AR,S$1,),"") -> 0 | T16: =IFERROR(VLOOKUP($A:$A,'Matrice Visualizzazione File 1'!$A:$AR,T$1,),"") | U16: =IFERROR(VLOOKUP($A:$A,'Matrice Visualizzazione File 1'!$A:$AR,U$1,),"") | V16: =IF(IFERROR(VLOOKUP($A:$A,'Matrice Visualizzazione File 1'!$A:$AR,V$1,),"")=0,"",IFERROR(VLOOKUP($A:$A,'Matrice Visualizzazione File 1'!$A:$AR,V$1,),"")) | W16: =IF(IFERROR(VLOOKUP($A:$A,'Matrice Visualizzazione File 1'!$A:$AR,W$1,),"")=0,"",IFERROR(VLOOKUP($A:$A,'Matrice Visualizzazione File 1'!$A:$AR,W$1,),"")) -> RN | X16: =IF(IFERROR(VLOOKUP($A:$A,'Matrice Visualizzazione File 1'!$A:$AR,X$1,),"")=0,"",IFERROR(VLOOKUP($A:$A,'Matrice Visualizzazione File 1'!$A:$AR,X$1,),"")) | Y16: =IF(IFERROR(VLOOKUP($A:$A,'Matrice Visualizzazione File 1'!$A:$AR,Y$1,),"")=0,"",IFERROR(VLOOKUP($A:$A,'Matrice Visualizzazione File 1'!$A:$AR,Y$1,),"")) | Z16: =IF(IFERROR(VLOOKUP($A:$A,'Matrice Visualizzazione File 1'!$A:$AR,Z$1,),"")=0,"",IFERROR(VLOOKUP($A:$A,'Matrice Visualizzazione File 1'!$A:$AR,Z$1,),"")) | AA16: =IF(IFERROR(VLOOKUP($A:$A,'Matrice Visualizzazione File 1'!$A:$AR,AA$1,),"")=0,"",IFERROR(VLOOKUP($A:$A,'Matrice Visualizzazione File 1'!$A:$AR,AA$1,),"")) | AB16: =IF(IFERROR(VLOOKUP($A:$A,'Matrice Visualizzazione File 1'!$A:$AR,AB$1,),"")=0,"",IFERROR(VLOOKUP($A:$A,'Matrice Visualizzazione File 1'!$A:$AR,AB$1,),"")) | AC16: =IF(IFERROR(VLOOKUP($A:$A,'Matrice Visualizzazione File 1'!$A:$AR,AC$1,),"")=0,"",IFERROR(VLOOKUP($A:$A,'Matrice Visualizzazione File 1'!$A:$AR,AC$1,),"")) | ... AN16: =IF(IFERROR(VLOOKUP($A:$A,'Matrice Visualizzazione File 1'!$A:$AR,AN$1,),"")=0,"",IFERROR(VLOOKUP($A:$A,'Matrice Visualizzazione File 1'!$A:$AR,AN$1,),""))
A17: =A16+1 -> 12 | B17: =IFERROR(VLOOKUP($A:$A,'Matrice Visualizzazione File 1'!$A:$AR,B$1,),"") -> AACCQ0E00 | C17: =IFERROR(VLOOKUP($A:$A,'Matrice Visualizzazione File 1'!$A:$AR,C$1,),"") -> AS35PCHHRA-NR | D17: =IFERROR(VLOOKUP($A:$A,'Matrice Visualizzazione File 1'!$A:$AR,D$1,),"") -> IU | E17: =_xlfn.TEXTJOIN("|",TRUE,Tabella_Traslata[[#This Row],[HN]:[CN]]) -> RN | F17: =_xlfn.TEXTJOIN("|",TRUE,Tabella_Traslata[[#This Row],[Sale office 1]:[Sale office 9]]) -> AGIR|ASI0 | G17: =IFERROR(VLOOKUP($A:$A,'Matrice Visualizzazione File 1'!$A:$AR,G$1,),"") -> Yes | H17: =IFERROR(VLOOKUP($A:$A,'Matrice Visualizzazione File 1'!$A:$AR,H$1,),"") -> Pearl Nordic | I17: =IFERROR(VLOOKUP($A:$A,'Matrice Visualizzazione File 1'!$A:$AR,I$1,),"") -> 0 | J17: =IFERROR(VLOOKUP($A:$A,'Matrice Visualizzazione File 1'!$A:$AR,J$1,),"") -> 5 | K17: =IFERROR(VLOOKUP($A:$A,'Matrice Visualizzazione File 1'!$A:$AR,K$1,),"") -> Catologue | L17: =_xlfn.TEXTJOIN("|",TRUE,Tabella_Traslata[[#This Row],[Codice Avviamento 1]:[Codice Avviamento 2]]) | M17: =_xlfn.TEXTJOIN("|",TRUE,Tabella_Traslata[[#This Row],[Accessorio 1]:[Accessorio 5]]) | N17: =IFERROR(VLOOKUP($A:$A,'Matrice Visualizzazione File 1'!$A:$AR,N$1,),"") | O17: =IFERROR(VLOOKUP($A:$A,'Matrice Visualizzazione File 1'!$A:$AR,O$1,),"") | P17: =IFERROR(VLOOKUP($A:$A,'Matrice Visualizzazione File 1'!$A:$AR,P$1,),"") | Q17: =IFERROR(VLOOKUP($A:$A,'Matrice Visualizzazione File 1'!$A:$AR,Q$1,),"") | R17: =IFERROR(VLOOKUP($A:$A,'Matrice Visualizzazione File 1'!$A:$AR,R$1,),"") | S17: =IFERROR(VLOOKUP($A:$A,'Matrice Visualizzazione File 1'!$A:$AR,S$1,),"") -> 0 | T17: =IFERROR(VLOOKUP($A:$A,'Matrice Visualizzazione File 1'!$A:$AR,T$1,),"") | U17: =IFERROR(VLOOKUP($A:$A,'Matrice Visualizzazione File 1'!$A:$AR,U$1,),"") | V17: =IF(IFERROR(VLOOKUP($A:$A,'Matrice Visualizzazione File 1'!$A:$AR,V$1,),"")=0,"",IFERROR(VLOOKUP($A:$A,'Matrice Visualizzazione File 1'!$A:$AR,V$1,),"")) | W17: =IF(IFERROR(VLOOKUP($A:$A,'Matrice Visualizzazione File 1'!$A:$AR,W$1,),"")=0,"",IFERROR(VLOOKUP($A:$A,'Matrice Visualizzazione File 1'!$A:$AR,W$1,),"")) -> RN | X17: =IF(IFERROR(VLOOKUP($A:$A,'Matrice Visualizzazione File 1'!$A:$AR,X$1,),"")=0,"",IFERROR(VLOOKUP($A:$A,'Matrice Visualizzazione File 1'!$A:$AR,X$1,),"")) | Y17: =IF(IFERROR(VLOOKUP($A:$A,'Matrice Visualizzazione File 1'!$A:$AR,Y$1,),"")=0,"",IFERROR(VLOOKUP($A:$A,'Matrice Visualizzazione File 1'!$A:$AR,Y$1,),"")) | Z17: =IF(IFERROR(VLOOKUP($A:$A,'Matrice Visualizzazione File 1'!$A:$AR,Z$1,),"")=0,"",IFERROR(VLOOKUP($A:$A,'Matrice Visualizzazione File 1'!$A:$AR,Z$1,),"")) | AA17: =IF(IFERROR(VLOOKUP($A:$A,'Matrice Visualizzazione File 1'!$A:$AR,AA$1,),"")=0,"",IFERROR(VLOOKUP($A:$A,'Matrice Visualizzazione File 1'!$A:$AR,AA$1,),"")) | AB17: =IF(IFERROR(VLOOKUP($A:$A,'Matrice Visualizzazione File 1'!$A:$AR,AB$1,),"")=0,"",IFERROR(VLOOKUP($A:$A,'Matrice Visualizzazione File 1'!$A:$AR,AB$1,),"")) | AC17: =IF(IFERROR(VLOOKUP($A:$A,'Matrice Visualizzazione File 1'!$A:$AR,AC$1,),"")=0,"",IFERROR(VLOOKUP($A:$A,'Matrice Visualizzazione File 1'!$A:$AR,AC$1,),"")) | ... AN17: =IF(IFERROR(VLOOKUP($A:$A,'Matrice Visualizzazione File 1'!$A:$AR,AN$1,),"")=0,"",IFERROR(VLOOKUP($A:$A,'Matrice Visualizzazione File 1'!$A:$AR,AN$1,),""))
A18: =A17+1 -> 13 | B18: =IFERROR(VLOOKUP($A:$A,'Matrice Visualizzazione File 1'!$A:$AR,B$1,),"") -> AACCR0E00 | C18: =IFERROR(VLOOKUP($A:$A,'Matrice Visualizzazione File 1'!$A:$AR,C$1,),"") -> AS50PDHHRA-NR | D18: =IFERROR(VLOOKUP($A:$A,'Matrice Visualizzazione File 1'!$A:$AR,D$1,),"") -> IU | E18: =_xlfn.TEXTJOIN("|",TRUE,Tabella_Traslata[[#This Row],[HN]:[CN]]) -> RN | F18: =_xlfn.TEXTJOIN("|",TRUE,Tabella_Traslata[[#This Row],[Sale office 1]:[Sale office 9]]) -> AGIR|ASI0 | G18: =IFERROR(VLOOKUP($A:$A,'Matrice Visualizzazione File 1'!$A:$AR,G$1,),"") -> Yes | H18: =IFERROR(VLOOKUP($A:$A,'Matrice Visualizzazione File 1'!$A:$AR,H$1,),"") -> Pearl Nordic | I18: =IFERROR(VLOOKUP($A:$A,'Matrice Visualizzazione File 1'!$A:$AR,I$1,),"") -> 0 | J18: =IFERROR(VLOOKUP($A:$A,'Matrice Visualizzazione File 1'!$A:$AR,J$1,),"") -> 5 | K18: =IFERROR(VLOOKUP($A:$A,'Matrice Visualizzazione File 1'!$A:$AR,K$1,),"") -> Catologue | L18: =_xlfn.TEXTJOIN("|",TRUE,Tabella_Traslata[[#This Row],[Codice Avviamento 1]:[Codice Avviamento 2]]) | M18: =_xlfn.TEXTJOIN("|",TRUE,Tabella_Traslata[[#This Row],[Accessorio 1]:[Accessorio 5]]) | N18: =IFERROR(VLOOKUP($A:$A,'Matrice Visualizzazione File 1'!$A:$AR,N$1,),"") | O18: =IFERROR(VLOOKUP($A:$A,'Matrice Visualizzazione File 1'!$A:$AR,O$1,),"") | P18: =IFERROR(VLOOKUP($A:$A,'Matrice Visualizzazione File 1'!$A:$AR,P$1,),"") | Q18: =IFERROR(VLOOKUP($A:$A,'Matrice Visualizzazione File 1'!$A:$AR,Q$1,),"") | R18: =IFERROR(VLOOKUP($A:$A,'Matrice Visualizzazione File 1'!$A:$AR,R$1,),"") | S18: =IFERROR(VLOOKUP($A:$A,'Matrice Visualizzazione File 1'!$A:$AR,S$1,),"") -> 0 | T18: =IFERROR(VLOOKUP($A:$A,'Matrice Visualizzazione File 1'!$A:$AR,T$1,),"") | U18: =IFERROR(VLOOKUP($A:$A,'Matrice Visualizzazione File 1'!$A:$AR,U$1,),"") | V18: =IF(IFERROR(VLOOKUP($A:$A,'Matrice Visualizzazione File 1'!$A:$AR,V$1,),"")=0,"",IFERROR(VLOOKUP($A:$A,'Matrice Visualizzazione File 1'!$A:$AR,V$1,),"")) | W18: =IF(IFERROR(VLOOKUP($A:$A,'Matrice Visualizzazione File 1'!$A:$AR,W$1,),"")=0,"",IFERROR(VLOOKUP($A:$A,'Matrice Visualizzazione File 1'!$A:$AR,W$1,),"")) -> RN | X18: =IF(IFERROR(VLOOKUP($A:$A,'Matrice Visualizzazione File 1'!$A:$AR,X$1,),"")=0,"",IFERROR(VLOOKUP($A:$A,'Matrice Visualizzazione File 1'!$A:$AR,X$1,),"")) | Y18: =IF(IFERROR(VLOOKUP($A:$A,'Matrice Visualizzazione File 1'!$A:$AR,Y$1,),"")=0,"",IFERROR(VLOOKUP($A:$A,'Matrice Visualizzazione File 1'!$A:$AR,Y$1,),"")) | Z18: =IF(IFERROR(VLOOKUP($A:$A,'Matrice Visualizzazione File 1'!$A:$AR,Z$1,),"")=0,"",IFERROR(VLOOKUP($A:$A,'Matrice Visualizzazione File 1'!$A:$AR,Z$1,),"")) | AA18: =IF(IFERROR(VLOOKUP($A:$A,'Matrice Visualizzazione File 1'!$A:$AR,AA$1,),"")=0,"",IFERROR(VLOOKUP($A:$A,'Matrice Visualizzazione File 1'!$A:$AR,AA$1,),"")) | AB18: =IF(IFERROR(VLOOKUP($A:$A,'Matrice Visualizzazione File 1'!$A:$AR,AB$1,),"")=0,"",IFERROR(VLOOKUP($A:$A,'Matrice Visualizzazione File 1'!$A:$AR,AB$1,),"")) | AC18: =IF(IFERROR(VLOOKUP($A:$A,'Matrice Visualizzazione File 1'!$A:$AR,AC$1,),"")=0,"",IFERROR(VLOOKUP($A:$A,'Matrice Visualizzazione File 1'!$A:$AR,AC$1,),"")) | ... AN18: =IF(IFERROR(VLOOKUP($A:$A,'Matrice Visualizzazione File 1'!$A:$AR,AN$1,),"")=0,"",IFERROR(VLOOKUP($A:$A,'Matrice Visualizzazione File 1'!$A:$AR,AN$1,),""))
... A2501: =A2500+1 -> 2496 | B2501: =IFERROR(VLOOKUP($A:$A,'Matrice Visualizzazione File 1'!$A:$AR,B$1,),"") | C2501: =IFERROR(VLOOKUP($A:$A,'Matrice Visualizzazione File 1'!$A:$AR,C$1,),"") | D2501: =IFERROR(VLOOKUP($A:$A,'Matrice Visualizzazione File 1'!$A:$AR,D$1,),"") | E2501: =_xlfn.TEXTJOIN("|",TRUE,Tabella_Traslata[[#This Row],[HN]:[CN]]) | F2501: =_xlfn.TEXTJOIN("|",TRUE,Tabella_Traslata[[#This Row],[Sale office 1]:[Sale office 9]]) | G2501: =IFERROR(VLOOKUP($A:$A,'Matrice Visualizzazione File 1'!$A:$AR,G$1,),"") | H2501: =IFERROR(VLOOKUP($A:$A,'Matrice Visualizzazione File 1'!$A:$AR,H$1,),"") | I2501: =IFERROR(VLOOKUP($A:$A,'Matrice Visualizzazione File 1'!$A:$AR,I$1,),"") | J2501: =IFERROR(VLOOKUP($A:$A,'Matrice Visualizzazione File 1'!$A:$AR,J$1,),"") | K2501: =IFERROR(VLOOKUP($A:$A,'Matrice Visualizzazione File 1'!$A:$AR,K$1,),"") | L2501: =_xlfn.TEXTJOIN("|",TRUE,Tabella_Traslata[[#This Row],[Codice Avviamento 1]:[Codice Avviamento 2]]) | M2501: =_xlfn.TEXTJOIN("|",TRUE,Tabella_Traslata[[#This Row],[Accessorio 1]:[Accessorio 5]]) | N2501: =IFERROR(VLOOKUP($A:$A,'Matrice Visualizzazione File 1'!$A:$AR,N$1,),"") | O2501: =IFERROR(VLOOKUP($A:$A,'Matrice Visualizzazione File 1'!$A:$AR,O$1,),"") | P2501: =IFERROR(VLOOKUP($A:$A,'Matrice Visualizzazione File 1'!$A:$AR,P$1,),"") | Q2501: =IFERROR(VLOOKUP($A:$A,'Matrice Visualizzazione File 1'!$A:$AR,Q$1,),"") | R2501: =IFERROR(VLOOKUP($A:$A,'Matrice Visualizzazione File 1'!$A:$AR,R$1,),"") | S2501: =IFERROR(VLOOKUP($A:$A,'Matrice Visualizzazione File 1'!$A:$AR,S$1,),"") | T2501: =IFERROR(VLOOKUP($A:$A,'Matrice Visualizzazione File 1'!$A:$AR,T$1,),"") | U2501: =IFERROR(VLOOKUP($A:$A,'Matrice Visualizzazione File 1'!$A:$AR,U$1,),"") | V2501: =IF(IFERROR(VLOOKUP($A:$A,'Matrice Visualizzazione File 1'!$A:$AR,V$1,),"")=0,"",IFERROR(VLOOKUP($A:$A,'Matrice Visualizzazione File 1'!$A:$AR,V$1,),"")) | W2501: =IF(IFERROR(VLOOKUP($A:$A,'Matrice Visualizzazione File 1'!$A:$AR,W$1,),"")=0,"",IFERROR(VLOOKUP($A:$A,'Matrice Visualizzazione File 1'!$A:$AR,W$1,),"")) | X2501: =IF(IFERROR(VLOOKUP($A:$A,'Matrice Visualizzazione File 1'!$A:$AR,X$1,),"")=0,"",IFERROR(VLOOKUP($A:$A,'Matrice Visualizzazione File 1'!$A:$AR,X$1,),"")) | Y2501: =IF(IFERROR(VLOOKUP($A:$A,'Matrice Visualizzazione File 1'!$A:$AR,Y$1,),"")=0,"",IFERROR(VLOOKUP($A:$A,'Matrice Visualizzazione File 1'!$A:$AR,Y$1,),"")) | Z2501: =IF(IFERROR(VLOOKUP($A:$A,'Matrice Visualizzazione File 1'!$A:$AR,Z$1,),"")=0,"",IFERROR(VLOOKUP($A:$A,'Matrice Visualizzazione File 1'!$A:$AR,Z$1,),"")) | AA2501: =IF(IFERROR(VLOOKUP($A:$A,'Matrice Visualizzazione File 1'!$A:$AR,AA$1,),"")=0,"",IFERROR(VLOOKUP($A:$A,'Matrice Visualizzazione File 1'!$A:$AR,AA$1,),"")) | AB2501: =IF(IFERROR(VLOOKUP($A:$A,'Matrice Visualizzazione File 1'!$A:$AR,AB$1,),"")=0,"",IFERROR(VLOOKUP($A:$A,'Matrice Visualizzazione File 1'!$A:$AR,AB$1,),"")) | AC2501: =IF(IFERROR(VLOOKUP($A:$A,'Matrice Visualizzazione File 1'!$A:$AR,AC$1,),"")=0,"",IFERROR(VLOOKUP($A:$A,'Matrice Visualizzazione File 1'!$A:$AR,AC$1,),"")) | ... AN2501: =IF(IFERROR(VLOOKUP($A:$A,'Matrice Visualizzazione File 1'!$A:$AR,AN$1,),"")=0,"",IFERROR(VLOOKUP($A:$A,'Matrice Visualizzazione File 1'!$A:$AR,AN$1,),""))

Sheet Export Tabella_Traslata
A1: ID | B1: Material | C1: Model | D1: Unit type | E1: SalesArea | F1: Sale office | G1: InCatalog | H1: Nota Descritiva | I1: Note Aggiuntive | J1: Min Q.tà | K1: Area | L1: Avviamenti | M1: Accessori | N1: Famiglia | O1: Tipologia | P1: Tecnologia | Q1: Catalogo | R1: Dimensionali | S1: Scheda Tecnica | T1: Descrizione Capitolato | U1: Descrizione Capitolato Opzionale
A2: 1 | B2: AB97Y0E00 | C2: AP71DFMHRA DIZUN | D2: IU | E2: HN|RN | F2: ABI0|AGIR|ASI0 | G2: Yes | H2: Cabinet | J2: 5 | K2: Catologue
A3: 2 | B3: AACKF0E00 | C3: 1U71WEMFRA DIZUN | D3: OU | E3: HN|RN | F3: ABI0|AGIR|ASI0 | G3: Yes | H3: Cabinet | J3: 5 | K3: Catologue
A4: 4 | B4: AAC160E00 | D4: IU | E4: HN|RN | F4: ABI0|AGIR|ASI0 | G4: Yes | H4: Expert Nordic | J4: 5 | K4: Catologue
A5: 5 | B5: AAC180E00 | C5: 1U25KEHFRA-NR | D5: OU | E5: HN|RN | F5: ABI0|AGIR|ASI0 | G5: Yes | H5: Expert Nordic | J5: 5 | K5: Catologue
A6: 6 | B6: AAC170E00 | C6: AS35XCHHRA-NR | D6: IU | E6: HN|RN | F6: ABI0|AGIR|ASI0 | G6: Yes | H6: Expert Nordic | J6: 5 | K6: Catologue
A7: 7 | B7: AAC190E00 | C7: 1U35KEHFRA-NR | D7: OU | E7: HN|RN | F7: ABI0|AGIR|ASI0 | G7: Yes | H7: Expert Nordic | J7: 5 | K7: Catologue
A8: 8 | B8: AABQN6E00 | C8: 1U35MEHFRA-1 | D8: OU | E8: RN | F8: AGIR|ASI0 | G8: Yes | H8: Flexis Nordic | J8: 5 | K8: Catologue
A9: 9 | B9: AAC152E00 | C9: 1U50KEFFRA-1 | D9: OU | E9: RN | F9: AGIR|ASI0 | G9: Yes | H9: Flexis Nordic | J9: 5 | K9: Catologue
A10: 11 | B10: AACCP0E00 | C10: AS25PCHHRA-NR | D10: IU | E10: RN | F10: AGIR|ASI0 | G10: Yes | H10: Pearl Nordic | J10: 5 | K10: Catologue
A11: 12 | B11: AACCQ0E00 | C11: AS35PCHHRA-NR | D11: IU | E11: RN | F11: AGIR|ASI0 | G11: Yes | H11: Pearl Nordic | J11: 5 | K11: Catologue
A12: 13 | B12: AACCR0E00 | C12: AS50PDHHRA-NR | D12: IU | E12: RN | F12: AGIR|ASI0 | G12: Yes | H12: Pearl Nordic | J12: 5 | K12: Catologue
A13: 14 | B13: AACCS0E00 | C13: 1U25KEFFRA-NR | D13: OU | E13: RN | F13: AGIR|ASI0 | G13: Yes | H13: Pearl Nordic | J13: 5 | K13: Catologue
A14: 15 | B14: AACCT0E00 | C14: 1U35KEFFRA-NR | D14: OU | E14: RN | F14: AGIR|ASI0 | G14: Yes | H14: Pearl Nordic | J14: 5 | K14: Catologue
A15: 16 | B15: AACCU0E00 | C15: 1U50WEFFRA-NR | D15: OU | E15: RN | F15: AGIR|ASI0 | G15: Yes | H15: Pearl Nordic | J15: 5 | K15: Catologue
A16: 18 | B16: AAC110E00 | C16: AS25PBBHRA | D16: IU | E16: RN | F16: AGIR|ASI0 | G16: Yes | H16: Pearl R29 | J16: 5 | K16: Catologue
... A23: 26 | B23: AAC150E00 | C23: 1U50S2SJ2FA-2 | D23: OU | E23: HN|RN | F23: ABI0|ACI0|AGIR|ASI0 | G23: Yes | H23: Mono SM+ | J23: 30 | K23: Catologue
A24: 27 | B24: AA9ZH1E2J | C24: 1U71S2SR2FA | D24: OU | E24: HN|RN | F24: ABI0|AGIR|ASI0 | G24: No | H24: Mono SM+ | I24: Phase Out - ESAUIRTO | J24: 10 | K24: Catologue
A25: 28 | B25: AE1XY1E00 | C25: 1U71S2ST1FA | D25: OU | E25: HN|RN | F25: ABI0|AGIR|ASI0 | G25: Yes | H25: Mono SM+ | I25: Sostituisce 1U71S2SR2FA | J25: 10 | K25: Catologue
A26: 29 | B26: AA9Z27E00 | C26: 1U105S2SS2FA | D26: OU | E26: HN|RN | F26: ABI0|AGIR|ASI0 | G26: No | H26: Mono SM+ | I26: Phase Out - ESAUIRTO | J26: 5 | K26: LCAC
A27: 30 | B27: AE1XF6E00 | C27: 1U105S2SQ1FA | D27: OU | E27: HN|RN | F27: ABI0|AGIR|ASI0 | G27: Yes | H27: Mono SM+ | I27: Sostituisce 1U15S2SS2FA | J27: 5 | K27: LCAC
A28: 31 | B28: AA9ZJ0E29 | C28: 1U105S2SS1FB | D28: OU | E28: HN|RN | F28: ABI0|AGIR|ASI0 | G28: Yes | H28: Mono SM+ | I28: Three Phase | J28: 5 | K28: LCAC
A29: 32 | B29: AA9Z35E00 | C29: 1U125S2SN2FA | D29: OU | E29: HN|RN | F29: ABI0|AGIR|ASI0 | G29: No | H29: Mono SM+ | I29: ESAUIRTO | J29: 5 | K29: LCAC
A30: 33 | B30: AE2182E00 | C30: 1U125S2SN3FA | D30: OU | E30: HN|RN | F30: ABI0|AGIR|ASI0 | G30: Yes | H30: Mono SM+ | I30: Sostituisce 1U125S2SN2FA | J30: 5 | K30: LCAC
A31: 34 | B31: AA9Z38E00 | C31: 1U125S2SN2FB | D31: OU | E31: HN|RN | F31: ABI0|AGIR|ASI0 | G31: Yes | H31: Mono SM+ | I31: Three Phase | J31: 5 | K31: LCAC
A32: 35 | B32: AE2181E00 | C32: 1U125S2SN3FB | D32: OU | E32: HN|RN | F32: ABI0|AGIR|ASI0 | G32: No | H32: Mono SM+ | I32: Three Phase - New model 226 | J32: 5 | K32: LCAC
A33: 36 | B33: AA9Z33E00 | C33: 1U140S2SN1FA | D33: OU | E33: HN|RN | F33: ABI0|AGIR|ASI0 | G33: Yes | H33: Mono SM+ | I33: Phase out | J33: 5 | K33: LCAC
A34: 37 | B34: AE2183E00 | C34: 1U140S2SN2FA | D34: OU | E34: HN|RN | F34: ABI0|AGIR|ASI0 | G34: No | H34: Mono SM+ | I34: New model 226 | J34: 5 | K34: LCAC
A35: 38 | B35: AA9Z34E00 | C35: 1U140S2SN1FB | D35: OU | E35: HN|RN | F35: ABI0|AGIR|ASI0 | G35: Yes | H35: Mono SM+ | I35: Three Phase phase out | J35: 5 | K35: LCAC
A36: 39 | B36: AE2180E00 | C36: 1U140S2SN2FB | D36: OU | E36: HN|RN | F36: ABI0|AGIR|ASI0 | G36: No | H36: Mono SM+ | I36: Three Phase - New model 226 | J36: 5 | K36: LCAC
A37: 40 | B37: AA9Z37E00 | C37: 1U140S2SP2FA | D37: OU | E37: HN|RN | F37: ABI0|AGIR|ASI0 | G37: Yes | H37: Mono SM+ | J37: 5 | K37: LCAC
A38: 41 | B38: AA9Z36E00 | C38: 1U140S2SP2FB | D38: OU | E38: HN|RN | F38: ABI0|AGIR|ASI0 | G38: Yes | H38: Mono SM+ | I38: Three Phase | J38: 5 | K38: LCAC
A39: 42 | B39: AA9Z73E00 | C39: 1U160S2SP1FB | D39: OU | E39: HN|RN | F39: ABI0|AGIR|ASI0 | G39: Yes | H39: Mono SM+ | I39: Three Phase | J39: 5 | K39: LCAC
A40: 43 | B40: AA9WE2E29 | C40: 1UH200W1ERK | D40: OU | E40: HN|RN | F40: ABI0|AGIR|ASI0 | G40: Yes | H40: Mono SM+ | J40: 5 | K40: LCAC
A41: 44 | B41: AA9WF0E29 | C41: 1UH250W1ERK | D41: OU | E41: HN|RN | F41: ABI0|AGIR|ASI0 | G41: Yes | H41: Mono SM+ | J41: 5 | K41: LCAC
A42: 46 | B42: AAB0S0E09 | C42: 2U40S2SM1FA | D42: OU | E42: HN|RN | F42: ABI0|ACI0|AGIR|ASI0 | G42: Yes | H42: Multi SM+ 1:2 | J42: 100 | K42: Catologue
A43: 47 | B43: AAB0T0E00 | C43: 2U50S2SM1FA-3 | D43: OU | E43: HN|RN | F43: ABI0|ACI0|AGIR|ASI0 | G43: Yes | H43: Multi SM+ 1:2 | J43: 100 | K43: Catologue
A44: 48 | B44: AAA2PJE00 | C44: 3U55S2SR5FA | D44: OU | E44: HN|RN | F44: ABI0|ACI0|AGIR|ASI0 | G44: Yes | H44: Multi SM+ 1:3 | J44: 100 | K44: Catologue
A45: 49 | B45: AAA2PHE00 | C45: 3U70S2SR5FA | D45: OU | E45: HN|RN | F45: ABI0|AGIR|ASI0 | G45: Yes | H45: Multi SM+ 1:3 | J45: 10 | K45: Catologue
A46: 50 | B46: AAA2R7E00 | C46: 4U75S2SR5FA | D46: OU | E46: HN|RN | F46: ABI0|AGIR|ASI0 | G46: Yes | H46: Multi SM+ 1:4 | J46: 10 | K46: Catologue
A47: 51 | B47: AAA2R5E00 | C47: 4U85S2SR5FA | D47: OU | E47: HN|RN | F47: ABI0|AGIR|ASI0 | G47: Yes | H47: Multi SM+ 1:4 | J47: 10 | K47: Catologue
A48: 52 | B48: AAA2R6E00 | C48: 5U90S2SS5FA | D48: OU | E48: HN|RN | F48: ABI0|AGIR|ASI0 | G48: Yes | H48: Multi SM+ 1:5 | J48: 10 | K48: Catologue
A49: 53 | B49: AAA2R8E00 | C49: 5U105S2SS5FA | D49: OU | E49: HN|RN | F49: ABI0|AGIR|ASI0 | G49: Yes | H49: Multi SM+ 1:5 | J49: 10 | K49: Catologue
A50: 54 | B50: AA9D74E00 | C50: 5U125S2SN1FA | D50: OU | E50: HN|RN | F50: ABI0|AGIR|ASI0 | G50: Yes | H50: Multi SM+ 1:5 | J50: 10 | K50: Catologue
A51: 56 | B51: AABQPAE00 | C51: AS20XCAHRA-MB | D51: IU | E51: HN|RN | F51: ABI0|ABI3|AGIR|ASI0 | G51: Yes | H51: Expert Black Black | J51: 5 | K51: Catologue
... A53: 58 | B53: AABQQ7E00 | C53: AS35XCAHRA-MB | D53: IU | E53: HN|RN | F53: ABI0|ABI3|AGIR|ASI0 | G53: Yes | H53: Expert Black Black | J53: 5 | K53: Catologue
A54: 59 | B54: AABQR6E00 | C54: AS42XCAHRA-MB | D54: IU | E54: HN | F54: ABI0|ABI3|ASI0 | G54: Yes | H54: Expert Black Black | I54: Phase Out - Clean Stock | J54: 5 | K54: Catologue
A55: 60 | B55: AABQQAE00 | C55: AS42XCAHRA-MB1 | D55: IU | E55: HN|RN | F55: ABI0|ABI3|AGIR|ASI0 | G55: No | H55: Expert Black Black | I55: New model Sostituisce AS35XCAHRA-MB | J55: 5 | K55: Catologue
A56: 61 | B56: AABQR5E00 | C56: AS50XCAHRA-MB | D56: IU | E56: HN|RN | F56: ABI0|ABI3|AGIR|ASI0 | G56: Yes | H56: Expert Black Black | J56: 5 | K56: Catologue
A57: 62 | B57: AAC101E00 | C57: AS71XCAHRA-MB | D57: IU | E57: HN|RN | F57: ABI0|AGIR|ASI0 | G57: Yes | H57: Expert Black Black | J57: 5 | K57: Catologue
A58: 64 | B58: AABQP1E00 | C58: AS20XCAHRA | D58: IU | E58: HN|RN | F58: ABI0|ABI3|AGIR|ASI0 | G58: Yes | H58: Expert White | J58: 5 | K58: Catologue
A59: 65 | B59: AABQP0E00 | C59: AS25XCAHRA | D59: IU | E59: HN|RN | F59: ABI0|ABI3|AGIR|ASI0 | G59: Yes | H59: Expert White | J59: 5 | K59: Catologue
A60: 66 | B60: AABQQ0E00 | C60: AS35XCAHRA | D60: IU | E60: HN|RN | F60: ABI0|ABI3|AGIR|ASI0 | G60: Yes | H60: Expert White | J60: 5 | K60: Catologue
A61: 67 | B61: AABQR1E00 | C61: AS42XCAHRA | D61: IU | E61: HN | F61: ABI0|ABI3|ASI0 | G61: No | H61: Expert White | I61: Phase Out - ESAUIRTO | J61: 5 | K61: Catologue
A62: 68 | B62: AABQQBE00 | C62: AS42XCAHRA-1 | D62: IU | E62: HN|RN | F62: ABI0|ABI3|AGIR|ASI0 | G62: Yes | H62: Expert White | I62: Sostituisce AS42XCAHRA | J62: 5 | K62: Catologue
A63: 69 | B63: AABQR0E00 | C63: AS50XCAHRA | D63: IU | E63: HN|RN | F63: ABI0|ABI3|AGIR|ASI0 | G63: Yes | H63: Expert White | J63: 5 | K63: Catologue
A64: 70 | B64: AAC100E00 | C64: AS71XCAHRA | D64: IU | E64: HN|RN | F64: ABI0|AGIR|ASI0 | G64: Yes | H64: Expert White | J64: 5 | K64: Catologue
A65: 72 | B65: AAA869E00 | C65: AS20S2SF1FA-MB3 | D65: IU | E65: HN|RN | F65: ABI0|ABI3|AGIR|ASI0 | G65: Yes | H65: Flexis Black | J65: 5 | K65: Catologue
A66: 73 | B66: AAA86BE00 | C66: AS25S2SF1FA-MB3 | D66: IU | E66: HN|RN | F66: ABI0|ABI3|AGIR|ASI0 | G66: Yes | H66: Flexis Black | J66: 5 | K66: Catologue
A67: 74 | B67: AAA6S9E00 | C67: AS35S2SF1FA-MB3 | D67: IU | E67: HN|RN | F67: ABI0|ABI3|AGIR|ASI0 | G67: Yes | H67: Flexis Black | J67: 5 | K67: Catologue
A68: 75 | B68: AAAYW1E00 | C68: AS42S2SF1FA-MB3 | D68: IU | E68: HN|RN | F68: ABI0|ABI3|AGIR|ASI0 | G68: Yes | H68: Flexis Black | J68: 5 | K68: Catologue
A69: 76 | B69: AAACL8E00 | C69: AS50S2SF1FA-MB3 | D69: IU | E69: HN|RN | F69: ABI0|ABI3|AGIR|ASI0 | G69: Yes | H69: Flexis Black | J69: 5 | K69: Catologue
A70: 77 | B70: AAACM9E00 | C70: AS71S2SF1FA-MB3 | D70: IU | E70: HN|RN | F70: ABI0|AGIR|ASI0 | G70: Yes | H70: Flexis Black | J70: 5 | K70: Catologue
A71: 79 | B71: AAA86AE00 | C71: AS20S2SF1FA-MW3 | D71: IU | E71: HN|RN | F71: ABI0|ABI3|AGIR|ASI0 | G71: Yes | H71: Flexis White | J71: 5 | K71: Catologue
A72: 80 | B72: AAA86CE00 | C72: AS25S2SF1FA-MW3 | D72: IU | E72: HN|RN | F72: ABI0|ABI3|AGIR|ASI0 | G72: Yes | H72: Flexis White | J72: 5 | K72: Catologue
A73: 81 | B73: AAA6S8E00 | C73: AS35S2SF1FA-MW3 | D73: IU | E73: HN|RN | F73: ABI0|ABI3|AGIR|ASI0 | G73: Yes | H73: Flexis White | J73: 5 | K73: Catologue
A74: 82 | B74: AAAYW2E00 | C74: AS42S2SF1FA-MW3 | D74: IU | E74: HN|RN | F74: ABI0|ABI3|AGIR|ASI0 | G74: Yes | H74: Flexis White | J74: 5 | K74: Catologue
... A77: 85 | B77: AAAVD0E00 | C77: AS105S2SF2FA-2 | D77: IU | E77: HN|RN | F77: ABI0|AGIR|ASI0 | G77: Yes | H77: IES | J77: 5 | K77: LCAC
A78: 87 | B78: AABF12E00 | C78: AS20PBAHRA | D78: IU | E78: HN|RN | F78: ABI0|AGIR|ASI0 | G78: Yes | H78: Pearl | I78: Phase Out - Clean Stock | J78: 0 | K78: Catologue
A79: 88 | B79: AABF10E00 | C79: AS25PBAHRA | D79: IU | E79: HN|RN | F79: ABI0|AGIR|ASI0 | G79: Yes | H79: Pearl | I79: Phase Out - Clean Stock | J79: 0 | K79: Catologue
A80: 89 | B80: AABF30E00 | C80: AS35PBAHRA | D80: IU | E80: HN|RN | F80: ABI0|AGIR|ASI0 | G80: Yes | H80: Pearl | I80: Phase Out - Clean Stock | J80: 0 | K80: Catologue
A81: 90 | B81: AABF23E00 | C81: 1U25YEGFRA-1 | D81: OU | E81: HN|RN | F81: ABI0|AGIR|ASI0 | G81: Yes | H81: Pearl | I81: Phase Out - Clean Stock | J81: 0 | K81: Catologue
A82: 91 | B82: AABF46E00 | C82: 1U35YEGFRA-1 | D82: OU | E82: HN|RN | F82: ABI0|AGIR|ASI0 | G82: Yes | H82: Pearl | I82: Phase Out - Clean Stock | J82: 0 | K82: Catologue
A83: 93 | B83: AACCXAE00 | C83: AS20PBAHRA-PRE | D83: IU | E83: HN|RN | F83: ABI0|ABI3|AGIR|ASI0 | G83: Yes | H83: Pearl | J83: 50 | K83: Catologue
A84: 94 | B84: AACCX0E00 | C84: AS25PBPHRA-PRE | D84: IU | E84: HN|RN | F84: ABI0|ABI3|AGIR|ASI0 | G84: Yes | H84: Pearl | J84: 150 | K84: Catologue
A85: 95 | B85: AACCY0E00 | C85: AS35PBPHRA-PRE | D85: IU | E85: HN|RN | F85: ABI0|ABI3|AGIR|ASI0 | G85: Yes | H85: Pearl | J85: 150 | K85: Catologue
A86: 96 | B86: AABF50E03 | C86: AS50PDAHRA | D86: IU | E86: HN | F86: ABI0|ABI3|ASI0 | G86: Yes | H86: Pearl | J86: 20 | K86: Catologue
A87: 97 | B87: AACQX0E00 | C87: AS50PDPHRA-PRE | D87: IU | E87: RN | F87: AGIR|ASI0 | G87: Yes | H87: Pearl | J87: 20 | K87: Catologue
A88: 98 | B88: AABQG0E00 | C88: AS68PDAHRA | D88: IU | E88: HN | F88: ABI0|ASI0 | G88: Yes | H88: Pearl | J88: 20 | K88: Catologue
A89: 99 | B89: AACQZ0E00 | C89: AS71PEPHRA-PRE | D89: IU | E89: RN | F89: AGIR|ASI0 | G89: Yes | H89: Pearl | J89: 20 | K89: Catologue
A90: 100 | B90: AACCV0E00 | C90: 1U25YEPFRA-PRE | D90: OU | E90: HN|RN | F90: ABI0|AGIR|ASI0 | G90: Yes | H90: Pearl | J90: 20 | K90: Catologue
A91: 101 | B91: AACCW0E00 | C91: 1U35MEPFRA-PRE | D91: OU | E91: HN|RN | F91: ABI0|AGIR|ASI0 | G91: Yes | H91: Pearl | J91: 20 | K91: Catologue
A92: 102 | B92: AABF60E03 | C92: 1U50MEGFRA | D92: OU | E92: HN | F92: ABI0|ASI0 | G92: Yes | H92: Pearl | J92: 20 | K92: Catologue
A93: 103 | B93: AACQY0E00 | C93: 1U50KEPFRA-PRE | D93: OU | E93: RN | F93: AGIR|ASI0 | G93: Yes | H93: Pearl | J93: 20 | K93: Catologue
A94: 104 | B94: AABSY0E00 | C94: 1U68WEGFRA | D94: OU | E94: HN | F94: ABI0|ASI0 | G94: Yes | H94: Pearl | J94: 20 | K94: Catologue
A95: 105 | B95: AACR00E00 | C95: 1U71WEPFRA-PRE | D95: OU | E95: RN | F95: AGIR|ASI0 | G95: Yes | H95: Pearl | J95: 20 | K95: Catologue
A96: 107 | B96: AA2JVPE00 | C96: AF25S2SD1FA(H) | D96: IU | E96: HN | F96: ABI0|ABI3|ASI0 | G96: No | H96: Console | I96: Phase Out - ESAUIRTO | J96: 0 | K96: Catologue
A97: 108 | B97: AA2JWCE00 | C97: AF25S2SD1FA(D) | D97: IU | E97: HN|RN | F97: ABI0|ABI3|AGIR|ASI0 | G97: Yes | H97: Console | I97: Sostituisce AF25S2SD1FA(H) | J97: 15 | K97: Catologue
A98: 109 | B98: AA2JVQE00 | C98: AF35S2SD1FA(H) | D98: IU | E98: HN | F98: ABI0|ABI3|ASI0 | G98: No | H98: Console | I98: Phase Out - ESAUIRTO | J98: 0 | K98: Catologue
A99: 110 | B99: AA2JWDE00 | C99: AF35S2SD1FA(D) | D99: IU | E99: HN|RN | F99: ABI0|ABI3|AGIR|ASI0 | G99: Yes | H99: Console | I99: Sostituisce AF35S2SD1FA(H) | J99: 15 | K99: Catologue
A100: 111 | B100: AA2JVRE00 | C100: AF42S2SD1FA(H) | D100: IU | E100: HN | F100: ABI0|ABI3|ASI0 | G100: No | H100: Console | I100: Phase Out - ESAUIRTO | J100: 0 | K100: Catologue
A101: 112 | B101: AA2JWBE00 | C101: AF42S2SD1FA(D) | D101: IU | E101: HN|RN | F101: ABI0|ABI3|AGIR|ASI0 | G101: Yes | H101: Console | I101: Sostiutisce AF42S2SD1FA(H) | J101: 15 | K101: Catologue
A102: 113 | B102: AE1X94E00 | C102: AF50S2SD1FA(H) | D102: IU | E102: HN | F102: ABI0|ABI3|ASI0 | G102: No | H102: Console | I102: Phase Out - ESAUIRTO | J102: 0 | K102: Catologue
A103: 114 | B103: AE1X93E00 | C103: AF50S2SD1FA(D) | D103: IU | E103: HN|RN | F103: ABI0|ABI3|AGIR|ASI0 | G103: Yes | H103: Console | I103: Sostituisce AF5S2SD1FA(H) | J103: 15 | K103: Catologue
A104: 116 | B104: AA9GL2E00 | C104: AD25S2SS1FA(H) | D104: IU | E104: HN|RN | F104: ABI0|ABI3|AGIR|ASI0 | G104: Yes | H104: Low Duct | J104: 15 | K104: Catologue
A105: 117 | B105: AA9GQ6E01 | C105: AD35S2SS1FA(H) | D105: IU | E105: HN|RN | F105: ABI0|ABI3|AGIR|ASI0 | G105: Yes | H105: Low Duct | J105: 15 | K105: Catologue
A106: 118 | B106: AA9JB3E00 | C106: AD50S2SS1FA(H) | D106: IU | E106: HN|RN | F106: ABI0|ABI3|AGIR|ASI0 | G106: Yes | H106: Low Duct | J106: 15 | K106: Catologue
A107: 119 | B107: AA9D19E00 | C107: AD71S2SS1FA(H) | D107: IU | E107: HN|RN | F107: ABI0|AGIR|ASI0 | G107: Yes | H107: Low Duct | J107: 15 | K107: Catologue
A108: 120 | B108: AA9CR2E5U | C108: P1B-890IA/D | D108: ACC | E108: HN|RN | F108: ABI0|ABI1|ABI3|AGIR|ASI0 | G108: Yes | H108: Duct Pannel | I108: AD25 - AD35 | J108: 15 | K108: Catologue
A109: 121 | B109: AA9CR1E5U | C109: P1B-1210IA/D | D109: ACC | E109: HN|RN | F109: ABI0|ABI1|ABI3|AGIR|ASI0 | G109: Yes | H109: Duct Pannel | I109: AD5 - AD71 | J109: 15 | K109: Catologue
...
